{
"meta":{"test_sets":[],"test_metrics":[],"learn_metrics":[{"best_value":"Min","name":"MultiClass"}],"launch_mode":"Train","parameters":"","iteration_count":1000,"learn_sets":["learn"],"name":"experiment"},
"iterations":[
{"learn":[1.303799019],"iteration":0,"passed_time":0.1582566257,"remaining_time":158.098369},
{"learn":[1.23090137],"iteration":1,"passed_time":0.1760398127,"remaining_time":87.84386651},
{"learn":[1.171766275],"iteration":2,"passed_time":0.1939467099,"remaining_time":64.4549566},
{"learn":[1.121956592],"iteration":3,"passed_time":0.2118525599,"remaining_time":52.75128742},
{"learn":[1.078952517],"iteration":4,"passed_time":0.2297208377,"remaining_time":45.71444669},
{"learn":[1.04230436],"iteration":5,"passed_time":0.2484568396,"remaining_time":41.16101642},
{"learn":[1.00799977],"iteration":6,"passed_time":0.2670394569,"remaining_time":37.88145438},
{"learn":[0.9735326589],"iteration":7,"passed_time":0.285288496,"remaining_time":35.37577351},
{"learn":[0.950093917],"iteration":8,"passed_time":0.3041179172,"remaining_time":33.48676177},
{"learn":[0.9236163562],"iteration":9,"passed_time":0.3226560518,"remaining_time":31.94294913},
{"learn":[0.9034377752],"iteration":10,"passed_time":0.3415787563,"remaining_time":30.71103545},
{"learn":[0.8833409648],"iteration":11,"passed_time":0.3615297347,"remaining_time":29.76594815},
{"learn":[0.8637154964],"iteration":12,"passed_time":0.3836598316,"remaining_time":29.12863491},
{"learn":[0.8476763748],"iteration":13,"passed_time":0.4041399846,"remaining_time":28.46300177},
{"learn":[0.8293655098],"iteration":14,"passed_time":0.4244946093,"remaining_time":27.87514601},
{"learn":[0.8139660511],"iteration":15,"passed_time":0.4460278449,"remaining_time":27.43071246},
{"learn":[0.7985555901],"iteration":16,"passed_time":0.4666310475,"remaining_time":26.9822541},
{"learn":[0.7858161641],"iteration":17,"passed_time":0.4872442916,"remaining_time":26.58188302},
{"learn":[0.7711746508],"iteration":18,"passed_time":0.5077965507,"remaining_time":26.2183377},
{"learn":[0.7590164998],"iteration":19,"passed_time":0.5291786771,"remaining_time":25.92975518},
{"learn":[0.7462195668],"iteration":20,"passed_time":0.5507882022,"remaining_time":25.67722143},
{"learn":[0.7362511136],"iteration":21,"passed_time":0.5714484185,"remaining_time":25.4034797},
{"learn":[0.7250439955],"iteration":22,"passed_time":0.5936646638,"remaining_time":25.21784246},
{"learn":[0.7155221692],"iteration":23,"passed_time":0.6158767177,"remaining_time":25.04565319},
{"learn":[0.7075026085],"iteration":24,"passed_time":0.6374961522,"remaining_time":24.86234994},
{"learn":[0.7007831304],"iteration":25,"passed_time":0.6574850212,"remaining_time":24.63040041},
{"learn":[0.6933806069],"iteration":26,"passed_time":0.6787507208,"remaining_time":24.46016487},
{"learn":[0.6876431162],"iteration":27,"passed_time":0.6996453811,"remaining_time":24.28768966},
{"learn":[0.6812521123],"iteration":28,"passed_time":0.7197424882,"remaining_time":24.098964},
{"learn":[0.6744627046],"iteration":29,"passed_time":0.7403750497,"remaining_time":23.93879327},
{"learn":[0.6667554608],"iteration":30,"passed_time":0.7617259148,"remaining_time":23.81007779},
{"learn":[0.6615696576],"iteration":31,"passed_time":0.7821067797,"remaining_time":23.65873008},
{"learn":[0.6551177813],"iteration":32,"passed_time":0.8020407528,"remaining_time":23.50222448},
{"learn":[0.6493601583],"iteration":33,"passed_time":0.8228883275,"remaining_time":23.37970954},
{"learn":[0.645129461],"iteration":34,"passed_time":0.8439548153,"remaining_time":23.26903991},
{"learn":[0.6409856267],"iteration":35,"passed_time":0.8651188146,"remaining_time":23.16595937},
{"learn":[0.6362761043],"iteration":36,"passed_time":0.8871877017,"remaining_time":23.09085829},
{"learn":[0.6309229386],"iteration":37,"passed_time":0.9095602968,"remaining_time":23.02623699},
{"learn":[0.6249631044],"iteration":38,"passed_time":0.9294222696,"remaining_time":22.90191798},
{"learn":[0.6211743033],"iteration":39,"passed_time":0.9496730355,"remaining_time":22.79215285},
{"learn":[0.6177298834],"iteration":40,"passed_time":0.9698048035,"remaining_time":22.68397089},
{"learn":[0.612393095],"iteration":41,"passed_time":0.98976894,"remaining_time":22.5761582},
{"learn":[0.6067929619],"iteration":42,"passed_time":1.010769091,"remaining_time":22.49548884},
{"learn":[0.6017419368],"iteration":43,"passed_time":1.031648922,"remaining_time":22.41491748},
{"learn":[0.5967681231],"iteration":44,"passed_time":1.051946591,"remaining_time":22.32464433},
{"learn":[0.5933300715],"iteration":45,"passed_time":1.072484196,"remaining_time":22.24238964},
{"learn":[0.5900258597],"iteration":46,"passed_time":1.093327006,"remaining_time":22.16894972},
{"learn":[0.587783732],"iteration":47,"passed_time":1.113210499,"remaining_time":22.0786749},
{"learn":[0.5838013172],"iteration":48,"passed_time":1.13229952,"remaining_time":21.97585396},
{"learn":[0.5792185257],"iteration":49,"passed_time":1.152651544,"remaining_time":21.90037934},
{"learn":[0.5760503684],"iteration":50,"passed_time":1.174155795,"remaining_time":21.84850685},
{"learn":[0.572552971],"iteration":51,"passed_time":1.196290632,"remaining_time":21.80929844},
{"learn":[0.5695169196],"iteration":52,"passed_time":1.217227413,"remaining_time":21.74932755},
{"learn":[0.5665020945],"iteration":53,"passed_time":1.237860258,"remaining_time":21.68547785},
{"learn":[0.5639418074],"iteration":54,"passed_time":1.259085037,"remaining_time":21.63337018},
{"learn":[0.5613449968],"iteration":55,"passed_time":1.279895916,"remaining_time":21.5753883},
{"learn":[0.5581782303],"iteration":56,"passed_time":1.301873841,"remaining_time":21.53801811},
{"learn":[0.5553327966],"iteration":57,"passed_time":1.323770193,"remaining_time":21.49985382},
{"learn":[0.5523011464],"iteration":58,"passed_time":1.34439545,"remaining_time":21.44196811},
{"learn":[0.5487178531],"iteration":59,"passed_time":1.364893916,"remaining_time":21.38333801},
{"learn":[0.5466459931],"iteration":60,"passed_time":1.385745425,"remaining_time":21.33139269},
{"learn":[0.5448792213],"iteration":61,"passed_time":1.406935111,"remaining_time":21.28556668},
{"learn":[0.5424520822],"iteration":62,"passed_time":1.427455324,"remaining_time":21.23056569},
{"learn":[0.5394159159],"iteration":63,"passed_time":1.448526295,"remaining_time":21.18469706},
{"learn":[0.5354403909],"iteration":64,"passed_time":1.469269189,"remaining_time":21.13487218},
{"learn":[0.5338046836],"iteration":65,"passed_time":1.489671283,"remaining_time":21.08110573},
{"learn":[0.5299372594],"iteration":66,"passed_time":1.510805923,"remaining_time":21.03853621},
{"learn":[0.52748951],"iteration":67,"passed_time":1.530531029,"remaining_time":20.97727822},
{"learn":[0.5257323284],"iteration":68,"passed_time":1.550794571,"remaining_time":20.92448907},
{"learn":[0.5228382042],"iteration":69,"passed_time":1.571105296,"remaining_time":20.87325608},
{"learn":[0.5204826982],"iteration":70,"passed_time":1.591444799,"remaining_time":20.82327067},
{"learn":[0.5180133491],"iteration":71,"passed_time":1.61117507,"remaining_time":20.76625646},
{"learn":[0.5157963325],"iteration":72,"passed_time":1.630835813,"remaining_time":20.7093808},
{"learn":[0.5136711639],"iteration":73,"passed_time":1.651633082,"remaining_time":20.66773289},
{"learn":[0.5117760503],"iteration":74,"passed_time":1.671982109,"remaining_time":20.62111267},
{"learn":[0.5095539769],"iteration":75,"passed_time":1.694773096,"remaining_time":20.6048729},
{"learn":[0.507935676],"iteration":76,"passed_time":1.714848272,"remaining_time":20.5559085},
{"learn":[0.5059793166],"iteration":77,"passed_time":1.736225752,"remaining_time":20.52307877},
{"learn":[0.5037960581],"iteration":78,"passed_time":1.756890972,"remaining_time":20.48223525},
{"learn":[0.5011203457],"iteration":79,"passed_time":1.777043524,"remaining_time":20.43600052},
{"learn":[0.4995929731],"iteration":80,"passed_time":1.797664113,"remaining_time":20.39572},
{"learn":[0.4981648662],"iteration":81,"passed_time":1.818570911,"remaining_time":20.35912312},
{"learn":[0.4959995344],"iteration":82,"passed_time":1.839480949,"remaining_time":20.32294012},
{"learn":[0.4935106226],"iteration":83,"passed_time":1.86026056,"remaining_time":20.28569849},
{"learn":[0.4920056685],"iteration":84,"passed_time":1.881056847,"remaining_time":20.24902371},
{"learn":[0.4902166976],"iteration":85,"passed_time":1.902614958,"remaining_time":20.22081478},
{"learn":[0.4885814766],"iteration":86,"passed_time":1.925039861,"remaining_time":20.20185509},
{"learn":[0.4868667652],"iteration":87,"passed_time":1.948027809,"remaining_time":20.18865184},
{"learn":[0.4852658334],"iteration":88,"passed_time":1.972654973,"remaining_time":20.19200764},
{"learn":[0.4835095945],"iteration":89,"passed_time":1.994274916,"remaining_time":20.16433526},
{"learn":[0.4811853866],"iteration":90,"passed_time":2.015705214,"remaining_time":20.13490153},
{"learn":[0.4796756339],"iteration":91,"passed_time":2.039320958,"remaining_time":20.1272112},
{"learn":[0.4774357029],"iteration":92,"passed_time":2.061566845,"remaining_time":20.10581859},
{"learn":[0.4762078721],"iteration":93,"passed_time":2.085082842,"remaining_time":20.09664952},
{"learn":[0.4742972791],"iteration":94,"passed_time":2.107971013,"remaining_time":20.08119755},
{"learn":[0.4730027338],"iteration":95,"passed_time":2.128738689,"remaining_time":20.04562265},
{"learn":[0.4710454158],"iteration":96,"passed_time":2.150693974,"remaining_time":20.02140885},
{"learn":[0.469839884],"iteration":97,"passed_time":2.172734598,"remaining_time":19.99802661},
{"learn":[0.4671785139],"iteration":98,"passed_time":2.193940555,"remaining_time":19.96707516},
{"learn":[0.4657764677],"iteration":99,"passed_time":2.21436798,"remaining_time":19.92931182},
{"learn":[0.4637654542],"iteration":100,"passed_time":2.236094241,"remaining_time":19.9034527},
{"learn":[0.4628642413],"iteration":101,"passed_time":2.256315295,"remaining_time":19.86442289},
{"learn":[0.4613780621],"iteration":102,"passed_time":2.276647063,"remaining_time":19.82672248},
{"learn":[0.4594610735],"iteration":103,"passed_time":2.298615574,"remaining_time":19.80345726},
{"learn":[0.457865219],"iteration":104,"passed_time":2.319300955,"remaining_time":19.76927957},
{"learn":[0.4563317357],"iteration":105,"passed_time":2.339874801,"remaining_time":19.73441578},
{"learn":[0.4542936396],"iteration":106,"passed_time":2.361088497,"remaining_time":19.70515914},
{"learn":[0.4520439581],"iteration":107,"passed_time":2.382622981,"remaining_time":19.67870091},
{"learn":[0.4494263962],"iteration":108,"passed_time":2.40357413,"remaining_time":19.64756468},
{"learn":[0.4484605605],"iteration":109,"passed_time":2.4233217,"remaining_time":19.60687558},
{"learn":[0.4467235229],"iteration":110,"passed_time":2.443015183,"remaining_time":19.56613061},
{"learn":[0.445514153],"iteration":111,"passed_time":2.463527762,"remaining_time":19.53225583},
{"learn":[0.4446312831],"iteration":112,"passed_time":2.484926379,"remaining_time":19.50557255},
{"learn":[0.4435443689],"iteration":113,"passed_time":2.505270568,"remaining_time":19.47078704},
{"learn":[0.4423893663],"iteration":114,"passed_time":2.524830287,"remaining_time":19.43021569},
{"learn":[0.4412116516],"iteration":115,"passed_time":2.54483031,"remaining_time":19.39336202},
{"learn":[0.4401306441],"iteration":116,"passed_time":2.565982844,"remaining_time":19.36549446},
{"learn":[0.4392128923],"iteration":117,"passed_time":2.587015502,"remaining_time":19.33684469},
{"learn":[0.4370496293],"iteration":118,"passed_time":2.608165063,"remaining_time":19.30918841},
{"learn":[0.4358449866],"iteration":119,"passed_time":2.62988894,"remaining_time":19.28585223},
{"learn":[0.4342353379],"iteration":120,"passed_time":2.652144645,"remaining_time":19.26640614},
{"learn":[0.4327220639],"iteration":121,"passed_time":2.674097804,"remaining_time":19.24473666},
{"learn":[0.4317680815],"iteration":122,"passed_time":2.694580564,"remaining_time":19.21257849},
{"learn":[0.4309134273],"iteration":123,"passed_time":2.716262062,"remaining_time":19.18907715},
{"learn":[0.4299803098],"iteration":124,"passed_time":2.737147757,"remaining_time":19.1600343},
{"learn":[0.4288460598],"iteration":125,"passed_time":2.757449678,"remaining_time":19.12707158},
{"learn":[0.427062641],"iteration":126,"passed_time":2.778227696,"remaining_time":19.09758094},
{"learn":[0.4248693353],"iteration":127,"passed_time":2.798990246,"remaining_time":19.06812105},
{"learn":[0.4231675074],"iteration":128,"passed_time":2.820278349,"remaining_time":19.04234451},
{"learn":[0.4218619368],"iteration":129,"passed_time":2.840184679,"remaining_time":19.00738978},
{"learn":[0.4200211713],"iteration":130,"passed_time":2.86076302,"remaining_time":18.97712263},
{"learn":[0.4186579984],"iteration":131,"passed_time":2.881961538,"remaining_time":18.95108042},
{"learn":[0.4171791665],"iteration":132,"passed_time":2.903048657,"remaining_time":18.92438485},
{"learn":[0.4159877128],"iteration":133,"passed_time":2.923223002,"remaining_time":18.89187403},
{"learn":[0.4148657264],"iteration":134,"passed_time":2.943921857,"remaining_time":18.86290671},
{"learn":[0.4139384987],"iteration":135,"passed_time":2.963997259,"remaining_time":18.83010024},
{"learn":[0.412764432],"iteration":136,"passed_time":2.984566146,"remaining_time":18.8005882},
{"learn":[0.4113394131],"iteration":137,"passed_time":3.005180418,"remaining_time":18.77148928},
{"learn":[0.4104709981],"iteration":138,"passed_time":3.02594198,"remaining_time":18.74342478},
{"learn":[0.4091204712],"iteration":139,"passed_time":3.046578051,"remaining_time":18.71469374},
{"learn":[0.4079541073],"iteration":140,"passed_time":3.067375874,"remaining_time":18.68706295},
{"learn":[0.407086211],"iteration":141,"passed_time":3.088598858,"remaining_time":18.66209733},
{"learn":[0.4057264156],"iteration":142,"passed_time":3.110158579,"remaining_time":18.63920211},
{"learn":[0.4047479874],"iteration":143,"passed_time":3.130551543,"remaining_time":18.60938973},
{"learn":[0.4036166582],"iteration":144,"passed_time":3.150849061,"remaining_time":18.57914447},
{"learn":[0.4024764107],"iteration":145,"passed_time":3.171200869,"remaining_time":18.54935303},
{"learn":[0.4011036763],"iteration":146,"passed_time":3.191926437,"remaining_time":18.52185885},
{"learn":[0.4002139753],"iteration":147,"passed_time":3.212332769,"remaining_time":18.49261837},
{"learn":[0.3992855607],"iteration":148,"passed_time":3.233225355,"remaining_time":18.46627367},
{"learn":[0.3983364738],"iteration":149,"passed_time":3.252835346,"remaining_time":18.43273363},
{"learn":[0.3971688134],"iteration":150,"passed_time":3.272891113,"remaining_time":18.40188447},
{"learn":[0.3965125859],"iteration":151,"passed_time":3.293665683,"remaining_time":18.37518749},
{"learn":[0.3951417962],"iteration":152,"passed_time":3.314703763,"remaining_time":18.35002672},
{"learn":[0.3937616545],"iteration":153,"passed_time":3.335546662,"remaining_time":18.32384725},
{"learn":[0.3925564402],"iteration":154,"passed_time":3.355806744,"remaining_time":18.29455934},
{"learn":[0.3914122819],"iteration":155,"passed_time":3.376821013,"remaining_time":18.26946753},
{"learn":[0.3901214627],"iteration":156,"passed_time":3.397834859,"remaining_time":18.24442539},
{"learn":[0.3896871451],"iteration":157,"passed_time":3.418090081,"remaining_time":18.21539145},
{"learn":[0.388599687],"iteration":158,"passed_time":3.439655238,"remaining_time":18.19339657},
{"learn":[0.3876328764],"iteration":159,"passed_time":3.460446286,"remaining_time":18.167343},
{"learn":[0.3865919688],"iteration":160,"passed_time":3.481472394,"remaining_time":18.14257974},
{"learn":[0.3851483633],"iteration":161,"passed_time":3.502582655,"remaining_time":18.11829793},
{"learn":[0.3839561162],"iteration":162,"passed_time":3.523278608,"remaining_time":18.09192758},
{"learn":[0.3830379005],"iteration":163,"passed_time":3.543116244,"remaining_time":18.0612511},
{"learn":[0.3822022076],"iteration":164,"passed_time":3.562982126,"remaining_time":18.03084894},
{"learn":[0.3811303208],"iteration":165,"passed_time":3.583031256,"remaining_time":18.00149438},
{"learn":[0.3803347063],"iteration":166,"passed_time":3.602912492,"remaining_time":17.97141381},
{"learn":[0.3793944433],"iteration":167,"passed_time":3.624340128,"remaining_time":17.94911302},
{"learn":[0.378300219],"iteration":168,"passed_time":3.644638456,"remaining_time":17.92126957},
{"learn":[0.3776261041],"iteration":169,"passed_time":3.664293099,"remaining_time":17.89037219},
{"learn":[0.3765797477],"iteration":170,"passed_time":3.685662736,"remaining_time":17.86792052},
{"learn":[0.3758927722],"iteration":171,"passed_time":3.707515305,"remaining_time":17.84780623},
{"learn":[0.3750250101],"iteration":172,"passed_time":3.728513431,"remaining_time":17.82358733},
{"learn":[0.3740486216],"iteration":173,"passed_time":3.748295311,"remaining_time":17.79363176},
{"learn":[0.3728910959],"iteration":174,"passed_time":3.767716774,"remaining_time":17.76209336},
{"learn":[0.3716060521],"iteration":175,"passed_time":3.788845066,"remaining_time":17.73868372},
{"learn":[0.3708371391],"iteration":176,"passed_time":3.808712902,"remaining_time":17.70943908},
{"learn":[0.3705019721],"iteration":177,"passed_time":3.828150438,"remaining_time":17.6783127},
{"learn":[0.3696437128],"iteration":178,"passed_time":3.849108429,"remaining_time":17.65429062},
{"learn":[0.3687290966],"iteration":179,"passed_time":3.870961043,"remaining_time":17.63437808},
{"learn":[0.3679528881],"iteration":180,"passed_time":3.892230159,"remaining_time":17.61180387},
{"learn":[0.3667922616],"iteration":181,"passed_time":3.91387259,"remaining_time":17.59092186},
{"learn":[0.3658690259],"iteration":182,"passed_time":3.933830722,"remaining_time":17.56251202},
{"learn":[0.3645904244],"iteration":183,"passed_time":3.955110215,"remaining_time":17.540054},
{"learn":[0.3636063224],"iteration":184,"passed_time":3.975901494,"remaining_time":17.51545794},
{"learn":[0.3630490668],"iteration":185,"passed_time":3.996684062,"remaining_time":17.49086466},
{"learn":[0.3623874122],"iteration":186,"passed_time":4.018093379,"remaining_time":17.46903699},
{"learn":[0.3617262117],"iteration":187,"passed_time":4.03932947,"remaining_time":17.44646558},
{"learn":[0.3610271391],"iteration":188,"passed_time":4.060807145,"remaining_time":17.42494494},
{"learn":[0.3600039459],"iteration":189,"passed_time":4.082919458,"remaining_time":17.40613032},
{"learn":[0.359602683],"iteration":190,"passed_time":4.104725214,"remaining_time":17.38598271},
{"learn":[0.3589711399],"iteration":191,"passed_time":4.125467208,"remaining_time":17.36134117},
{"learn":[0.3581037219],"iteration":192,"passed_time":4.146291609,"remaining_time":17.33708461},
{"learn":[0.357300472],"iteration":193,"passed_time":4.167674775,"remaining_time":17.31518489},
{"learn":[0.3565755286],"iteration":194,"passed_time":4.187603393,"remaining_time":17.2872858},
{"learn":[0.3554650453],"iteration":195,"passed_time":4.208912498,"remaining_time":17.26513086},
{"learn":[0.3548855244],"iteration":196,"passed_time":4.230751791,"remaining_time":17.24514562},
{"learn":[0.353836812],"iteration":197,"passed_time":4.25301596,"remaining_time":17.22686263},
{"learn":[0.3532968131],"iteration":198,"passed_time":4.273535132,"remaining_time":17.20151578},
{"learn":[0.3527876559],"iteration":199,"passed_time":4.294442561,"remaining_time":17.17777025},
{"learn":[0.3521336697],"iteration":200,"passed_time":4.315258687,"remaining_time":17.15369001},
{"learn":[0.3510379684],"iteration":201,"passed_time":4.336735838,"remaining_time":17.13225346},
{"learn":[0.3505104541],"iteration":202,"passed_time":4.356813081,"remaining_time":17.10532032},
{"learn":[0.3497698866],"iteration":203,"passed_time":4.37731272,"remaining_time":17.08010257},
{"learn":[0.3492248322],"iteration":204,"passed_time":4.398669352,"remaining_time":17.05825432},
{"learn":[0.3485266253],"iteration":205,"passed_time":4.42030571,"remaining_time":17.037489},
{"learn":[0.3481191302],"iteration":206,"passed_time":4.440294038,"remaining_time":17.0104018},
{"learn":[0.3476617226],"iteration":207,"passed_time":4.460722009,"remaining_time":16.98505688},
{"learn":[0.3469361607],"iteration":208,"passed_time":4.481585476,"remaining_time":16.96140723},
{"learn":[0.3459409498],"iteration":209,"passed_time":4.50285864,"remaining_time":16.93932536},
{"learn":[0.3450247514],"iteration":210,"passed_time":4.52339112,"remaining_time":16.91448149},
{"learn":[0.344349598],"iteration":211,"passed_time":4.544293288,"remaining_time":16.89105241},
{"learn":[0.3437253825],"iteration":212,"passed_time":4.565567809,"remaining_time":16.86902284},
{"learn":[0.3427792417],"iteration":213,"passed_time":4.586170938,"remaining_time":16.84453438},
{"learn":[0.3422409867],"iteration":214,"passed_time":4.605529053,"remaining_time":16.81553631},
{"learn":[0.3412027465],"iteration":215,"passed_time":4.626754331,"remaining_time":16.79340461},
{"learn":[0.3404430565],"iteration":216,"passed_time":4.648228362,"remaining_time":16.77217884},
{"learn":[0.3401622933],"iteration":217,"passed_time":4.668940788,"remaining_time":16.74821879},
{"learn":[0.339199958],"iteration":218,"passed_time":4.691564564,"remaining_time":16.73110468},
{"learn":[0.3386192308],"iteration":219,"passed_time":4.714140452,"remaining_time":16.71377069},
{"learn":[0.3377611765],"iteration":220,"passed_time":4.735337688,"remaining_time":16.69152968},
{"learn":[0.3370007888],"iteration":221,"passed_time":4.756895818,"remaining_time":16.67056282},
{"learn":[0.3361515853],"iteration":222,"passed_time":4.779125321,"remaining_time":16.65192993},
{"learn":[0.3356465673],"iteration":223,"passed_time":4.799923104,"remaining_time":16.62830504},
{"learn":[0.3349177789],"iteration":224,"passed_time":4.821265659,"remaining_time":16.60658172},
{"learn":[0.3342132637],"iteration":225,"passed_time":4.841682004,"remaining_time":16.58168969},
{"learn":[0.3336242591],"iteration":226,"passed_time":4.864503178,"remaining_time":16.56502624},
{"learn":[0.3327763527],"iteration":227,"passed_time":4.889705539,"remaining_time":16.55637139},
{"learn":[0.3319987211],"iteration":228,"passed_time":4.910077074,"remaining_time":16.53130753},
{"learn":[0.3314917993],"iteration":229,"passed_time":4.931497577,"remaining_time":16.50979624},
{"learn":[0.3309585351],"iteration":230,"passed_time":4.95200836,"remaining_time":16.48525727},
{"learn":[0.3304082196],"iteration":231,"passed_time":4.972945398,"remaining_time":16.46216407},
{"learn":[0.32909723],"iteration":232,"passed_time":4.994620098,"remaining_time":16.44151766},
{"learn":[0.3282357496],"iteration":233,"passed_time":5.01651826,"remaining_time":16.42159396},
{"learn":[0.3273721454],"iteration":234,"passed_time":5.038397457,"remaining_time":16.40159172},
{"learn":[0.3265986337],"iteration":235,"passed_time":5.059482496,"remaining_time":16.37900266},
{"learn":[0.3258647318],"iteration":236,"passed_time":5.081523178,"remaining_time":16.35950289},
{"learn":[0.3252003367],"iteration":237,"passed_time":5.102071005,"remaining_time":16.33520213},
{"learn":[0.3244912003],"iteration":238,"passed_time":5.123215427,"remaining_time":16.31283238},
{"learn":[0.3235703324],"iteration":239,"passed_time":5.143918558,"remaining_time":16.28907543},
{"learn":[0.3227799918],"iteration":240,"passed_time":5.164572378,"remaining_time":16.26518853},
{"learn":[0.3222293427],"iteration":241,"passed_time":5.184620956,"remaining_time":16.23943258},
{"learn":[0.3214611843],"iteration":242,"passed_time":5.205898108,"remaining_time":16.2175509},
{"learn":[0.3206432409],"iteration":243,"passed_time":5.227103019,"remaining_time":16.19545034},
{"learn":[0.3201031697],"iteration":244,"passed_time":5.2483294,"remaining_time":16.17342325},
{"learn":[0.3194128817],"iteration":245,"passed_time":5.270076013,"remaining_time":16.15299721},
{"learn":[0.3181773553],"iteration":246,"passed_time":5.292847083,"remaining_time":16.13568362},
{"learn":[0.317102236],"iteration":247,"passed_time":5.315175466,"remaining_time":16.11698367},
{"learn":[0.3159758281],"iteration":248,"passed_time":5.336546339,"remaining_time":16.09536667},
{"learn":[0.3154205659],"iteration":249,"passed_time":5.357812704,"remaining_time":16.07343811},
{"learn":[0.314598585],"iteration":250,"passed_time":5.379187764,"remaining_time":16.05183919},
{"learn":[0.313803952],"iteration":251,"passed_time":5.400228084,"remaining_time":16.02924844},
{"learn":[0.31307358],"iteration":252,"passed_time":5.421406266,"remaining_time":16.007077},
{"learn":[0.3123513371],"iteration":253,"passed_time":5.444409119,"remaining_time":15.99027245},
{"learn":[0.3117526682],"iteration":254,"passed_time":5.465648009,"remaining_time":15.96826575},
{"learn":[0.3113657708],"iteration":255,"passed_time":5.485664935,"remaining_time":15.94271372},
{"learn":[0.3105709456],"iteration":256,"passed_time":5.506255718,"remaining_time":15.91886381},
{"learn":[0.3102097514],"iteration":257,"passed_time":5.527341304,"remaining_time":15.8964622},
{"learn":[0.3095501877],"iteration":258,"passed_time":5.548100184,"remaining_time":15.87313605},
{"learn":[0.3088696669],"iteration":259,"passed_time":5.57011541,"remaining_time":15.8534054},
{"learn":[0.3082315835],"iteration":260,"passed_time":5.592253078,"remaining_time":15.83400393},
{"learn":[0.3073246816],"iteration":261,"passed_time":5.613496793,"remaining_time":15.81206348},
{"learn":[0.3069512433],"iteration":262,"passed_time":5.635029334,"remaining_time":15.79093771},
{"learn":[0.3063331618],"iteration":263,"passed_time":5.658539985,"remaining_time":15.77532359},
{"learn":[0.3054441704],"iteration":264,"passed_time":5.679907741,"remaining_time":15.75370638},
{"learn":[0.3048030629],"iteration":265,"passed_time":5.700978967,"remaining_time":15.73127279},
{"learn":[0.3041058881],"iteration":266,"passed_time":5.723298777,"remaining_time":15.71227717},
{"learn":[0.3037209201],"iteration":267,"passed_time":5.744319735,"remaining_time":15.68970913},
{"learn":[0.303058784],"iteration":268,"passed_time":5.764575144,"remaining_time":15.66507223},
{"learn":[0.3027139977],"iteration":269,"passed_time":5.784125272,"remaining_time":15.63856092},
{"learn":[0.3020572709],"iteration":270,"passed_time":5.806298918,"remaining_time":15.61915834},
{"learn":[0.3015417938],"iteration":271,"passed_time":5.827943385,"remaining_time":15.59831906},
{"learn":[0.3011815556],"iteration":272,"passed_time":5.849335156,"remaining_time":15.57680095},
{"learn":[0.3009093751],"iteration":273,"passed_time":5.870371586,"remaining_time":15.55434223},
{"learn":[0.3002736842],"iteration":274,"passed_time":5.890838604,"remaining_time":15.53039268},
{"learn":[0.2991625475],"iteration":275,"passed_time":5.911738608,"remaining_time":15.50760417},
{"learn":[0.298608784],"iteration":276,"passed_time":5.931640038,"remaining_time":15.48222292},
{"learn":[0.2979633117],"iteration":277,"passed_time":5.952419921,"remaining_time":15.45916253},
{"learn":[0.2975655204],"iteration":278,"passed_time":5.973535907,"remaining_time":15.43698706},
{"learn":[0.2970789656],"iteration":279,"passed_time":5.993953569,"remaining_time":15.41302346},
{"learn":[0.2963187937],"iteration":280,"passed_time":6.01477404,"remaining_time":15.39011578},
{"learn":[0.2957881031],"iteration":281,"passed_time":6.034813776,"remaining_time":15.36523508},
{"learn":[0.2952685201],"iteration":282,"passed_time":6.055658477,"remaining_time":15.34242801},
{"learn":[0.294770856],"iteration":283,"passed_time":6.076206996,"remaining_time":15.31888806},
{"learn":[0.2943406539],"iteration":284,"passed_time":6.096551689,"remaining_time":15.29485775},
{"learn":[0.2935876888],"iteration":285,"passed_time":6.119018185,"remaining_time":15.27615029},
{"learn":[0.2932037995],"iteration":286,"passed_time":6.1401707,"remaining_time":15.2541523},
{"learn":[0.292769867],"iteration":287,"passed_time":6.160231712,"remaining_time":15.22946173},
{"learn":[0.2923679357],"iteration":288,"passed_time":6.181059637,"remaining_time":15.20668997},
{"learn":[0.291640231],"iteration":289,"passed_time":6.201911342,"remaining_time":15.18398984},
{"learn":[0.2910417681],"iteration":290,"passed_time":6.222259805,"remaining_time":15.1600763},
{"learn":[0.2906710475],"iteration":291,"passed_time":6.242526267,"remaining_time":15.13598835},
{"learn":[0.2901433967],"iteration":292,"passed_time":6.262792608,"remaining_time":15.11192619},
{"learn":[0.2897952483],"iteration":293,"passed_time":6.283273238,"remaining_time":15.08840444},
{"learn":[0.2892171655],"iteration":294,"passed_time":6.304304997,"remaining_time":15.06622042},
{"learn":[0.2887611359],"iteration":295,"passed_time":6.324936357,"remaining_time":15.04309188},
{"learn":[0.2880526757],"iteration":296,"passed_time":6.345522531,"remaining_time":15.0198732},
{"learn":[0.2872299265],"iteration":297,"passed_time":6.366419026,"remaining_time":14.99740321},
{"learn":[0.2862419809],"iteration":298,"passed_time":6.387261404,"remaining_time":14.97481687},
{"learn":[0.285562085],"iteration":299,"passed_time":6.407389623,"remaining_time":14.95057579},
{"learn":[0.2853326918],"iteration":300,"passed_time":6.427581867,"remaining_time":14.92651071},
{"learn":[0.2850954224],"iteration":301,"passed_time":6.448788785,"remaining_time":14.90481646},
{"learn":[0.2844505018],"iteration":302,"passed_time":6.469544606,"remaining_time":14.88208776},
{"learn":[0.2838835976],"iteration":303,"passed_time":6.489397145,"remaining_time":14.85730399},
{"learn":[0.2835483407],"iteration":304,"passed_time":6.509273859,"remaining_time":14.83260765},
{"learn":[0.2829965189],"iteration":305,"passed_time":6.529101153,"remaining_time":14.80783072},
{"learn":[0.2826310244],"iteration":306,"passed_time":6.550030519,"remaining_time":14.78557378},
{"learn":[0.2819159945],"iteration":307,"passed_time":6.572000461,"remaining_time":14.76566337},
{"learn":[0.2814829826],"iteration":308,"passed_time":6.592505135,"remaining_time":14.74246294},
{"learn":[0.2810373634],"iteration":309,"passed_time":6.614147634,"remaining_time":14.72181247},
{"learn":[0.2805919697],"iteration":310,"passed_time":6.635066269,"remaining_time":14.69955196},
{"learn":[0.2803757441],"iteration":311,"passed_time":6.654925598,"remaining_time":14.67496414},
{"learn":[0.2798532194],"iteration":312,"passed_time":6.676399083,"remaining_time":14.65394943},
{"learn":[0.2794270435],"iteration":313,"passed_time":6.697092813,"remaining_time":14.63122825},
{"learn":[0.2784895348],"iteration":314,"passed_time":6.718141713,"remaining_time":14.6092923},
{"learn":[0.2781045359],"iteration":315,"passed_time":6.739505164,"remaining_time":14.58804282},
{"learn":[0.2778196997],"iteration":316,"passed_time":6.76204366,"remaining_time":14.56932435},
{"learn":[0.27720513],"iteration":317,"passed_time":6.784232812,"remaining_time":14.54983264},
{"learn":[0.276765596],"iteration":318,"passed_time":6.804092848,"remaining_time":14.52535182},
{"learn":[0.2761566072],"iteration":319,"passed_time":6.825114438,"remaining_time":14.50336818},
{"learn":[0.2756217695],"iteration":320,"passed_time":6.845557257,"remaining_time":14.48016628},
{"learn":[0.2752983086],"iteration":321,"passed_time":6.866140107,"remaining_time":14.45727637},
{"learn":[0.274630408],"iteration":322,"passed_time":6.887590955,"remaining_time":14.43622005},
{"learn":[0.2742609931],"iteration":323,"passed_time":6.908073589,"remaining_time":14.41314119},
{"learn":[0.2737578238],"iteration":324,"passed_time":6.929377155,"remaining_time":14.39178332},
{"learn":[0.2735327136],"iteration":325,"passed_time":6.950391598,"remaining_time":14.36982803},
{"learn":[0.2730518785],"iteration":326,"passed_time":6.970626991,"remaining_time":14.34627512},
{"learn":[0.2727131076],"iteration":327,"passed_time":6.990632588,"remaining_time":14.32227164},
{"learn":[0.2721835919],"iteration":328,"passed_time":7.011958625,"remaining_time":14.30098552},
{"learn":[0.2717783828],"iteration":329,"passed_time":7.033053823,"remaining_time":14.27923049},
{"learn":[0.271407891],"iteration":330,"passed_time":7.05332918,"remaining_time":14.25582242},
{"learn":[0.2710276088],"iteration":331,"passed_time":7.074541102,"remaining_time":14.23431764},
{"learn":[0.2706783229],"iteration":332,"passed_time":7.094940771,"remaining_time":14.21118767},
{"learn":[0.2703943396],"iteration":333,"passed_time":7.115756942,"remaining_time":14.18890456},
{"learn":[0.2698470285],"iteration":334,"passed_time":7.13539725,"remaining_time":14.16429603},
{"learn":[0.2693106902],"iteration":335,"passed_time":7.156560122,"remaining_time":14.14272596},
{"learn":[0.2689369517],"iteration":336,"passed_time":7.17844185,"remaining_time":14.12257254},
{"learn":[0.2684843707],"iteration":337,"passed_time":7.198698984,"remaining_time":14.099227},
{"learn":[0.2681143688],"iteration":338,"passed_time":7.218582558,"remaining_time":14.0751713},
{"learn":[0.2676245955],"iteration":339,"passed_time":7.238873568,"remaining_time":14.05193104},
{"learn":[0.2671107927],"iteration":340,"passed_time":7.259019404,"remaining_time":14.02842753},
{"learn":[0.2664188496],"iteration":341,"passed_time":7.278760605,"remaining_time":14.00416514},
{"learn":[0.26583522],"iteration":342,"passed_time":7.298980454,"remaining_time":13.98084594},
{"learn":[0.2652824793],"iteration":343,"passed_time":7.319166497,"remaining_time":13.9574803},
{"learn":[0.2649814119],"iteration":344,"passed_time":7.340253798,"remaining_time":13.93584417},
{"learn":[0.26451378],"iteration":345,"passed_time":7.361146473,"remaining_time":13.91384333},
{"learn":[0.2635742134],"iteration":346,"passed_time":7.382118885,"remaining_time":13.89199894},
{"learn":[0.2632070042],"iteration":347,"passed_time":7.401772443,"remaining_time":13.8676886},
{"learn":[0.2629002182],"iteration":348,"passed_time":7.420619923,"remaining_time":13.84190135},
{"learn":[0.2626297886],"iteration":349,"passed_time":7.4419275,"remaining_time":13.8207225},
{"learn":[0.262130977],"iteration":350,"passed_time":7.461590651,"remaining_time":13.79650237},
{"learn":[0.2618113728],"iteration":351,"passed_time":7.481140582,"remaining_time":13.77209971},
{"learn":[0.2612795327],"iteration":352,"passed_time":7.500913466,"remaining_time":13.74813318},
{"learn":[0.260736628],"iteration":353,"passed_time":7.520244556,"remaining_time":13.72338413},
{"learn":[0.2599604799],"iteration":354,"passed_time":7.541351647,"remaining_time":13.70189243},
{"learn":[0.2595798831],"iteration":355,"passed_time":7.561148119,"remaining_time":13.67803199},
{"learn":[0.2590743865],"iteration":356,"passed_time":7.580435301,"remaining_time":13.65327703},
{"learn":[0.258503517],"iteration":357,"passed_time":7.60013784,"remaining_time":13.62929747},
{"learn":[0.2581539155],"iteration":358,"passed_time":7.619309791,"remaining_time":13.60439436},
{"learn":[0.2578415296],"iteration":359,"passed_time":7.639834292,"remaining_time":13.58192763},
{"learn":[0.2575800925],"iteration":360,"passed_time":7.659682946,"remaining_time":13.55827535},
{"learn":[0.2572262512],"iteration":361,"passed_time":7.679020658,"remaining_time":13.53374359},
{"learn":[0.2564189893],"iteration":362,"passed_time":7.698330274,"remaining_time":13.50919114},
{"learn":[0.2562010492],"iteration":363,"passed_time":7.716837937,"remaining_time":13.48326629},
{"learn":[0.2557557491],"iteration":364,"passed_time":7.735639289,"remaining_time":13.45789301},
{"learn":[0.2555026955],"iteration":365,"passed_time":7.75694755,"remaining_time":13.43689822},
{"learn":[0.2550414782],"iteration":366,"passed_time":7.776544462,"remaining_time":13.41294998},
{"learn":[0.2546818939],"iteration":367,"passed_time":7.795473961,"remaining_time":13.38787919},
{"learn":[0.2542706958],"iteration":368,"passed_time":7.814619726,"remaining_time":13.36321151},
{"learn":[0.2537327954],"iteration":369,"passed_time":7.833758927,"remaining_time":13.3385625},
{"learn":[0.2531680428],"iteration":370,"passed_time":7.853542194,"remaining_time":13.31503515},
{"learn":[0.2528317999],"iteration":371,"passed_time":7.87832283,"remaining_time":13.29996435},
{"learn":[0.2524790198],"iteration":372,"passed_time":7.898155859,"remaining_time":13.27652473},
{"learn":[0.2521735096],"iteration":373,"passed_time":7.916680578,"remaining_time":13.25091455},
{"learn":[0.251649146],"iteration":374,"passed_time":7.936671746,"remaining_time":13.22778624},
{"learn":[0.2512606154],"iteration":375,"passed_time":7.957128725,"remaining_time":13.20544767},
{"learn":[0.2507015454],"iteration":376,"passed_time":7.976527361,"remaining_time":13.18137015},
{"learn":[0.2504451566],"iteration":377,"passed_time":7.994806726,"remaining_time":13.15547562},
{"learn":[0.249886722],"iteration":378,"passed_time":8.013795139,"remaining_time":13.13078306},
{"learn":[0.2495078192],"iteration":379,"passed_time":8.03299055,"remaining_time":13.10645827},
{"learn":[0.2491764705],"iteration":380,"passed_time":8.080717685,"remaining_time":13.12851508},
{"learn":[0.2486792916],"iteration":381,"passed_time":8.116775709,"remaining_time":13.13132824},
{"learn":[0.2483921668],"iteration":382,"passed_time":8.139732468,"remaining_time":13.11283272},
{"learn":[0.2481158464],"iteration":383,"passed_time":8.160454987,"remaining_time":13.09072987},
{"learn":[0.2478179461],"iteration":384,"passed_time":8.180277945,"remaining_time":13.06719724},
{"learn":[0.2473169438],"iteration":385,"passed_time":8.200857588,"remaining_time":13.04488746},
{"learn":[0.2468110522],"iteration":386,"passed_time":8.2217352,"remaining_time":13.0230586},
{"learn":[0.2463210889],"iteration":387,"passed_time":8.241938206,"remaining_time":13.00017057},
{"learn":[0.2458483332],"iteration":388,"passed_time":8.261272566,"remaining_time":12.97593197},
{"learn":[0.2455928599],"iteration":389,"passed_time":8.282118901,"remaining_time":12.95408341},
{"learn":[0.2450143352],"iteration":390,"passed_time":8.303135647,"remaining_time":12.93250539},
{"learn":[0.2446707504],"iteration":391,"passed_time":8.323315539,"remaining_time":12.90963226},
{"learn":[0.2441885433],"iteration":392,"passed_time":8.343668658,"remaining_time":12.8870404},
{"learn":[0.2435714406],"iteration":393,"passed_time":8.363034655,"remaining_time":12.86294163},
{"learn":[0.2432396461],"iteration":394,"passed_time":8.383348916,"remaining_time":12.84031923},
{"learn":[0.2422682285],"iteration":395,"passed_time":8.403587583,"remaining_time":12.81759318},
{"learn":[0.2416552847],"iteration":396,"passed_time":8.426204468,"remaining_time":12.79849193},
{"learn":[0.2412276066],"iteration":397,"passed_time":8.445200198,"remaining_time":12.77389578},
{"learn":[0.2407674198],"iteration":398,"passed_time":8.465729407,"remaining_time":12.75163753},
{"learn":[0.2403928307],"iteration":399,"passed_time":8.48557654,"remaining_time":12.72836481},
{"learn":[0.2401266424],"iteration":400,"passed_time":8.50556907,"remaining_time":12.70532637},
{"learn":[0.2394529874],"iteration":401,"passed_time":8.524346759,"remaining_time":12.68049592},
{"learn":[0.2391505063],"iteration":402,"passed_time":8.543186158,"remaining_time":12.65578694},
{"learn":[0.2387831335],"iteration":403,"passed_time":8.563402688,"remaining_time":12.63313862},
{"learn":[0.2383991475],"iteration":404,"passed_time":8.584054971,"remaining_time":12.61114249},
{"learn":[0.2380628345],"iteration":405,"passed_time":8.603829272,"remaining_time":12.58786844},
{"learn":[0.2378250567],"iteration":406,"passed_time":8.623389714,"remaining_time":12.5643},
{"learn":[0.2371720761],"iteration":407,"passed_time":8.643425847,"remaining_time":12.54144143},
{"learn":[0.2365190155],"iteration":408,"passed_time":8.663804992,"remaining_time":12.5190923},
{"learn":[0.2361819243],"iteration":409,"passed_time":8.684027079,"remaining_time":12.49652677},
{"learn":[0.235737411],"iteration":410,"passed_time":8.703893197,"remaining_time":12.47346251},
{"learn":[0.2353925483],"iteration":411,"passed_time":8.723077119,"remaining_time":12.44944016},
{"learn":[0.2350243283],"iteration":412,"passed_time":8.741801658,"remaining_time":12.42478831},
{"learn":[0.2347312926],"iteration":413,"passed_time":8.762384691,"remaining_time":12.40279572},
{"learn":[0.234593889],"iteration":414,"passed_time":8.784763753,"remaining_time":12.38334168},
{"learn":[0.2341831358],"iteration":415,"passed_time":8.805501799,"remaining_time":12.36156983},
{"learn":[0.2338379345],"iteration":416,"passed_time":8.825685056,"remaining_time":12.33902731},
{"learn":[0.2335156635],"iteration":417,"passed_time":8.844945833,"remaining_time":12.31521166},
{"learn":[0.2332270407],"iteration":418,"passed_time":8.865306695,"remaining_time":12.29294317},
{"learn":[0.2325387339],"iteration":419,"passed_time":8.88372864,"remaining_time":12.26800622},
{"learn":[0.2320918091],"iteration":420,"passed_time":8.903881754,"remaining_time":12.24548108},
{"learn":[0.2314658108],"iteration":421,"passed_time":8.924709419,"remaining_time":12.2238911},
{"learn":[0.2312371948],"iteration":422,"passed_time":8.94304301,"remaining_time":12.19890264},
{"learn":[0.2307789308],"iteration":423,"passed_time":8.96317429,"remaining_time":12.17638771},
{"learn":[0.2302405355],"iteration":424,"passed_time":8.982320653,"remaining_time":12.15255147},
{"learn":[0.2299529413],"iteration":425,"passed_time":9.001795303,"remaining_time":12.12917959},
{"learn":[0.229626562],"iteration":426,"passed_time":9.021569953,"remaining_time":12.10622853},
{"learn":[0.2288954203],"iteration":427,"passed_time":9.040740906,"remaining_time":12.08248551},
{"learn":[0.228591759],"iteration":428,"passed_time":9.061126577,"remaining_time":12.0603806},
{"learn":[0.2281177101],"iteration":429,"passed_time":9.081544449,"remaining_time":12.03832636},
{"learn":[0.2275813664],"iteration":430,"passed_time":9.101403205,"remaining_time":12.01554159},
{"learn":[0.2272256678],"iteration":431,"passed_time":9.121385413,"remaining_time":11.99293267},
{"learn":[0.2269606833],"iteration":432,"passed_time":9.14044923,"remaining_time":11.96913329},
{"learn":[0.22656612],"iteration":433,"passed_time":9.161673149,"remaining_time":11.94817282},
{"learn":[0.2261031757],"iteration":434,"passed_time":9.182050673,"remaining_time":11.92611179},
{"learn":[0.2258171357],"iteration":435,"passed_time":9.201966034,"remaining_time":11.90346065},
{"learn":[0.225596338],"iteration":436,"passed_time":9.220970198,"remaining_time":11.8796481},
{"learn":[0.2250360285],"iteration":437,"passed_time":9.240450898,"remaining_time":11.85646896},
{"learn":[0.2243991336],"iteration":438,"passed_time":9.260538466,"remaining_time":11.83408219},
{"learn":[0.2240579418],"iteration":439,"passed_time":9.28102066,"remaining_time":11.81220811},
{"learn":[0.2236512973],"iteration":440,"passed_time":9.301867468,"remaining_time":11.79080253},
{"learn":[0.2233452437],"iteration":441,"passed_time":9.321925398,"remaining_time":11.76840356},
{"learn":[0.2232128847],"iteration":442,"passed_time":9.342707279,"remaining_time":11.7469254},
{"learn":[0.2227140387],"iteration":443,"passed_time":9.362820415,"remaining_time":11.72461295},
{"learn":[0.2225258437],"iteration":444,"passed_time":9.382340394,"remaining_time":11.7015706},
{"learn":[0.2221810503],"iteration":445,"passed_time":9.401151853,"remaining_time":11.67766396},
{"learn":[0.2218380791],"iteration":446,"passed_time":9.420700355,"remaining_time":11.65469194},
{"learn":[0.2216984747],"iteration":447,"passed_time":9.440988069,"remaining_time":11.63264601},
{"learn":[0.2214299491],"iteration":448,"passed_time":9.460937598,"remaining_time":11.61019291},
{"learn":[0.220831747],"iteration":449,"passed_time":9.480627491,"remaining_time":11.5874336},
{"learn":[0.2205986668],"iteration":450,"passed_time":9.500160248,"remaining_time":11.56449662},
{"learn":[0.2202076682],"iteration":451,"passed_time":9.519328607,"remaining_time":11.54113291},
{"learn":[0.2198511382],"iteration":452,"passed_time":9.538481763,"remaining_time":11.51776937},
{"learn":[0.2194224258],"iteration":453,"passed_time":9.558005968,"remaining_time":11.49487061},
{"learn":[0.2190048595],"iteration":454,"passed_time":9.578055614,"remaining_time":11.47261606},
{"learn":[0.21872551],"iteration":455,"passed_time":9.59788707,"remaining_time":11.45011089},
{"learn":[0.2185194474],"iteration":456,"passed_time":9.617187032,"remaining_time":11.4269859},
{"learn":[0.2180919656],"iteration":457,"passed_time":9.636272841,"remaining_time":11.40362419},
{"learn":[0.2179034349],"iteration":458,"passed_time":9.656320112,"remaining_time":11.38141434},
{"learn":[0.2175482902],"iteration":459,"passed_time":9.67597266,"remaining_time":11.35875051},
{"learn":[0.2170910935],"iteration":460,"passed_time":9.696773134,"remaining_time":11.33744191},
{"learn":[0.2168787348],"iteration":461,"passed_time":9.715660015,"remaining_time":11.31390712},
{"learn":[0.216320826],"iteration":462,"passed_time":9.735977239,"remaining_time":11.29205136},
{"learn":[0.2161226416],"iteration":463,"passed_time":9.756666131,"remaining_time":11.27063157},
{"learn":[0.2158099963],"iteration":464,"passed_time":9.776562319,"remaining_time":11.24830288},
{"learn":[0.2153881764],"iteration":465,"passed_time":9.795962183,"remaining_time":11.22541589},
{"learn":[0.2150885036],"iteration":466,"passed_time":9.815701486,"remaining_time":11.20293125},
{"learn":[0.2148177539],"iteration":467,"passed_time":9.834996589,"remaining_time":11.17995339},
{"learn":[0.2145505412],"iteration":468,"passed_time":9.855788331,"remaining_time":11.15868572},
{"learn":[0.2141400166],"iteration":469,"passed_time":9.876898759,"remaining_time":11.13777945},
{"learn":[0.2137864819],"iteration":470,"passed_time":9.900975981,"remaining_time":11.12020445},
{"learn":[0.2134758213],"iteration":471,"passed_time":9.921391237,"remaining_time":11.09850545},
{"learn":[0.2131761694],"iteration":472,"passed_time":9.941216404,"remaining_time":11.07615443},
{"learn":[0.2129462296],"iteration":473,"passed_time":9.960437062,"remaining_time":11.05314324},
{"learn":[0.2125230443],"iteration":474,"passed_time":9.978241446,"remaining_time":11.02858265},
{"learn":[0.2122220331],"iteration":475,"passed_time":9.999415235,"remaining_time":11.00775963},
{"learn":[0.2118636701],"iteration":476,"passed_time":10.01800951,"remaining_time":10.98410686},
{"learn":[0.2115733282],"iteration":477,"passed_time":10.03850301,"remaining_time":10.96254932},
{"learn":[0.2111793245],"iteration":478,"passed_time":10.0586703,"remaining_time":10.9406414},
{"learn":[0.2107063423],"iteration":479,"passed_time":10.07785133,"remaining_time":10.91767227},
{"learn":[0.2104402462],"iteration":480,"passed_time":10.09715072,"remaining_time":10.89484662},
{"learn":[0.2099578977],"iteration":481,"passed_time":10.11611279,"remaining_time":10.87167308},
{"learn":[0.2094577195],"iteration":482,"passed_time":10.13684555,"remaining_time":10.85041232},
{"learn":[0.2090603715],"iteration":483,"passed_time":10.15765075,"remaining_time":10.82923096},
{"learn":[0.2088193285],"iteration":484,"passed_time":10.17671143,"remaining_time":10.80619873},
{"learn":[0.2083597758],"iteration":485,"passed_time":10.19598505,"remaining_time":10.78340806},
{"learn":[0.2079852768],"iteration":486,"passed_time":10.21580557,"remaining_time":10.76120792},
{"learn":[0.2077965076],"iteration":487,"passed_time":10.23629073,"remaining_time":10.73971486},
{"learn":[0.2075917214],"iteration":488,"passed_time":10.25567562,"remaining_time":10.71707616},
{"learn":[0.2072393075],"iteration":489,"passed_time":10.27509407,"remaining_time":10.69448567},
{"learn":[0.2069093953],"iteration":490,"passed_time":10.29353218,"remaining_time":10.67089181},
{"learn":[0.2064892681],"iteration":491,"passed_time":10.31313617,"remaining_time":10.64852271},
{"learn":[0.206197083],"iteration":492,"passed_time":10.33228714,"remaining_time":10.62569894},
{"learn":[0.205971781],"iteration":493,"passed_time":10.35198518,"remaining_time":10.60345041},
{"learn":[0.2056087996],"iteration":494,"passed_time":10.37129959,"remaining_time":10.58082079},
{"learn":[0.2052167488],"iteration":495,"passed_time":10.39092211,"remaining_time":10.55851763},
{"learn":[0.2048472778],"iteration":496,"passed_time":10.41029112,"remaining_time":10.53596868},
{"learn":[0.2047060793],"iteration":497,"passed_time":10.4299098,"remaining_time":10.51368418},
{"learn":[0.2044163903],"iteration":498,"passed_time":10.45117342,"remaining_time":10.49306189},
{"learn":[0.2041375632],"iteration":499,"passed_time":10.4713707,"remaining_time":10.4713707},
{"learn":[0.203839249],"iteration":500,"passed_time":10.4904921,"remaining_time":10.44861389},
{"learn":[0.2036367063],"iteration":501,"passed_time":10.50901591,"remaining_time":10.42527873},
{"learn":[0.2034444188],"iteration":502,"passed_time":10.52847074,"remaining_time":10.40288262},
{"learn":[0.2032620413],"iteration":503,"passed_time":10.54790743,"remaining_time":10.38048033},
{"learn":[0.2027939334],"iteration":504,"passed_time":10.56860148,"remaining_time":10.35932224},
{"learn":[0.2024787659],"iteration":505,"passed_time":10.58876971,"remaining_time":10.33765264},
{"learn":[0.2022832313],"iteration":506,"passed_time":10.6082419,"remaining_time":10.31531214},
{"learn":[0.2017805058],"iteration":507,"passed_time":10.62799502,"remaining_time":10.29325502},
{"learn":[0.2015364244],"iteration":508,"passed_time":10.64702651,"remaining_time":10.27051084},
{"learn":[0.2013888307],"iteration":509,"passed_time":10.66645813,"remaining_time":10.24816565},
{"learn":[0.2010511818],"iteration":510,"passed_time":10.68614298,"remaining_time":10.2260742},
{"learn":[0.2008454274],"iteration":511,"passed_time":10.70584605,"remaining_time":10.20400952},
{"learn":[0.2006124973],"iteration":512,"passed_time":10.72499912,"remaining_time":10.18143191},
{"learn":[0.2004131649],"iteration":513,"passed_time":10.74516403,"remaining_time":10.15982435},
{"learn":[0.200093613],"iteration":514,"passed_time":10.76440508,"remaining_time":10.13735236},
{"learn":[0.1997854263],"iteration":515,"passed_time":10.78418623,"remaining_time":10.11539949},
{"learn":[0.1996459465],"iteration":516,"passed_time":10.80389929,"remaining_time":10.0933914},
{"learn":[0.1990261158],"iteration":517,"passed_time":10.82533461,"remaining_time":10.07299475},
{"learn":[0.19871101],"iteration":518,"passed_time":10.84813957,"remaining_time":10.05386345},
{"learn":[0.1983623026],"iteration":519,"passed_time":10.87171601,"remaining_time":10.03543017},
{"learn":[0.1979881188],"iteration":520,"passed_time":10.89144674,"remaining_time":10.01344144},
{"learn":[0.1975522082],"iteration":521,"passed_time":10.9115033,"remaining_time":9.991759729},
{"learn":[0.196946817],"iteration":522,"passed_time":10.93206839,"remaining_time":9.970548038},
{"learn":[0.1966166693],"iteration":523,"passed_time":10.95261548,"remaining_time":9.949322457},
{"learn":[0.196138594],"iteration":524,"passed_time":10.97230648,"remaining_time":9.927324913},
{"learn":[0.1957833419],"iteration":525,"passed_time":10.99157014,"remaining_time":9.904951036},
{"learn":[0.1954476327],"iteration":526,"passed_time":11.01179632,"remaining_time":9.883452865},
{"learn":[0.1950190615],"iteration":527,"passed_time":11.03034328,"remaining_time":9.860458384},
{"learn":[0.1947091443],"iteration":528,"passed_time":11.05075863,"remaining_time":9.839144267},
{"learn":[0.1942924263],"iteration":529,"passed_time":11.07033054,"remaining_time":9.817085577},
{"learn":[0.1939260207],"iteration":530,"passed_time":11.08993961,"remaining_time":9.795069069},
{"learn":[0.193623953],"iteration":531,"passed_time":11.10998204,"remaining_time":9.773442848},
{"learn":[0.1932968348],"iteration":532,"passed_time":11.13047653,"remaining_time":9.752218646},
{"learn":[0.1930463619],"iteration":533,"passed_time":11.15132201,"remaining_time":9.731303473},
{"learn":[0.1925120159],"iteration":534,"passed_time":11.1714009,"remaining_time":9.709722274},
{"learn":[0.1921885305],"iteration":535,"passed_time":11.1918116,"remaining_time":9.688433925},
{"learn":[0.191721072],"iteration":536,"passed_time":11.21247916,"remaining_time":9.667370296},
{"learn":[0.1915441258],"iteration":537,"passed_time":11.23216539,"remaining_time":9.645465446},
{"learn":[0.1913493322],"iteration":538,"passed_time":11.250646,"remaining_time":9.622537674},
{"learn":[0.1910415297],"iteration":539,"passed_time":11.27025,"remaining_time":9.60058333},
{"learn":[0.1906555251],"iteration":540,"passed_time":11.29012,"remaining_time":9.578863364},
{"learn":[0.1902738838],"iteration":541,"passed_time":11.31146834,"remaining_time":9.55839945},
{"learn":[0.1897354932],"iteration":542,"passed_time":11.33222529,"remaining_time":9.53743454},
{"learn":[0.1895211692],"iteration":543,"passed_time":11.3524836,"remaining_time":9.516052426},
{"learn":[0.1890574528],"iteration":544,"passed_time":11.37272522,"remaining_time":9.494660502},
{"learn":[0.1886189293],"iteration":545,"passed_time":11.39328723,"remaining_time":9.473539202},
{"learn":[0.1881102565],"iteration":546,"passed_time":11.41431209,"remaining_time":9.452803245},
{"learn":[0.1878299152],"iteration":547,"passed_time":11.43411915,"remaining_time":9.431061782},
{"learn":[0.1876176291],"iteration":548,"passed_time":11.45402775,"remaining_time":9.409410771},
{"learn":[0.1872407472],"iteration":549,"passed_time":11.47378268,"remaining_time":9.387640377},
{"learn":[0.1869736153],"iteration":550,"passed_time":11.49427035,"remaining_time":9.366474386},
{"learn":[0.1866661669],"iteration":551,"passed_time":11.51531621,"remaining_time":9.345763877},
{"learn":[0.1865060246],"iteration":552,"passed_time":11.53469764,"remaining_time":9.323706776},
{"learn":[0.1861870561],"iteration":553,"passed_time":11.55411023,"remaining_time":9.30168441},
{"learn":[0.1858616904],"iteration":554,"passed_time":11.57368462,"remaining_time":9.279801179},
{"learn":[0.1855523773],"iteration":555,"passed_time":11.59406467,"remaining_time":9.258569626},
{"learn":[0.1851051788],"iteration":556,"passed_time":11.61444516,"remaining_time":9.237341483},
{"learn":[0.1848685348],"iteration":557,"passed_time":11.63452622,"remaining_time":9.215879188},
{"learn":[0.1845014015],"iteration":558,"passed_time":11.65475431,"remaining_time":9.194537839},
{"learn":[0.1840680203],"iteration":559,"passed_time":11.67479972,"remaining_time":9.173056919},
{"learn":[0.1838839033],"iteration":560,"passed_time":11.6950407,"remaining_time":9.151734169},
{"learn":[0.1836378483],"iteration":561,"passed_time":11.71477902,"remaining_time":9.130023509},
{"learn":[0.1834626009],"iteration":562,"passed_time":11.73330142,"remaining_time":9.107376061},
{"learn":[0.183094442],"iteration":563,"passed_time":11.75339611,"remaining_time":9.085958697},
{"learn":[0.1828484973],"iteration":564,"passed_time":11.77277841,"remaining_time":9.063997536},
{"learn":[0.1823893476],"iteration":565,"passed_time":11.79406046,"remaining_time":9.043502188},
{"learn":[0.1820748352],"iteration":566,"passed_time":11.8143725,"remaining_time":9.022263304},
{"learn":[0.1817212897],"iteration":567,"passed_time":11.83328674,"remaining_time":8.999964564},
{"learn":[0.1814417882],"iteration":568,"passed_time":11.85318554,"remaining_time":8.978423497},
{"learn":[0.181285524],"iteration":569,"passed_time":11.87511706,"remaining_time":8.958421641},
{"learn":[0.1808730248],"iteration":570,"passed_time":11.8969226,"remaining_time":8.938318378},
{"learn":[0.1806712152],"iteration":571,"passed_time":11.91760097,"remaining_time":8.917365764},
{"learn":[0.1804586953],"iteration":572,"passed_time":11.93837808,"remaining_time":8.896487678},
{"learn":[0.1802108548],"iteration":573,"passed_time":11.95835969,"remaining_time":8.875019559},
{"learn":[0.1799719587],"iteration":574,"passed_time":11.97773925,"remaining_time":8.853111616},
{"learn":[0.179602147],"iteration":575,"passed_time":11.9975433,"remaining_time":8.83152493},
{"learn":[0.1793541252],"iteration":576,"passed_time":12.01820058,"remaining_time":8.810569919},
{"learn":[0.1790829104],"iteration":577,"passed_time":12.03835155,"remaining_time":8.789246287},
{"learn":[0.1789401566],"iteration":578,"passed_time":12.05857271,"remaining_time":8.767977742},
{"learn":[0.1787160459],"iteration":579,"passed_time":12.07863589,"remaining_time":8.746598404},
{"learn":[0.1785952302],"iteration":580,"passed_time":12.0989345,"remaining_time":8.725393386},
{"learn":[0.1784110204],"iteration":581,"passed_time":12.11874446,"remaining_time":8.703840525},
{"learn":[0.178045086],"iteration":582,"passed_time":12.13913632,"remaining_time":8.682709852},
{"learn":[0.1777557188],"iteration":583,"passed_time":12.15934519,"remaining_time":8.661451367},
{"learn":[0.1775038442],"iteration":584,"passed_time":12.17974645,"remaining_time":8.640332954},
{"learn":[0.1771853636],"iteration":585,"passed_time":12.20001536,"remaining_time":8.619123477},
{"learn":[0.1770078313],"iteration":586,"passed_time":12.22073039,"remaining_time":8.598231092},
{"learn":[0.176786526],"iteration":587,"passed_time":12.24111637,"remaining_time":8.577108746},
{"learn":[0.1765760921],"iteration":588,"passed_time":12.26210952,"remaining_time":8.556412585},
{"learn":[0.1762687302],"iteration":589,"passed_time":12.28237626,"remaining_time":8.535210619},
{"learn":[0.1757681946],"iteration":590,"passed_time":12.30338736,"remaining_time":8.514526952},
{"learn":[0.1753758156],"iteration":591,"passed_time":12.32473138,"remaining_time":8.494071626},
{"learn":[0.1752508324],"iteration":592,"passed_time":12.34384152,"remaining_time":8.472080096},
{"learn":[0.1750944474],"iteration":593,"passed_time":12.36264005,"remaining_time":8.449885285},
{"learn":[0.1747590646],"iteration":594,"passed_time":12.38160957,"remaining_time":8.427818277},
{"learn":[0.1745336417],"iteration":595,"passed_time":12.40190356,"remaining_time":8.40665946},
{"learn":[0.1742338504],"iteration":596,"passed_time":12.42249652,"remaining_time":8.385705354},
{"learn":[0.1741070023],"iteration":597,"passed_time":12.44219824,"remaining_time":8.364153331},
{"learn":[0.1738225497],"iteration":598,"passed_time":12.46105639,"remaining_time":8.342042758},
{"learn":[0.1735192861],"iteration":599,"passed_time":12.48158043,"remaining_time":8.321053622},
{"learn":[0.1732004375],"iteration":600,"passed_time":12.50205363,"remaining_time":8.300032274},
{"learn":[0.1730747688],"iteration":601,"passed_time":12.52270298,"remaining_time":8.279129212},
{"learn":[0.1727119562],"iteration":602,"passed_time":12.54215637,"remaining_time":8.257439601},
{"learn":[0.172424431],"iteration":603,"passed_time":12.56157247,"remaining_time":8.235732945},
{"learn":[0.1722688784],"iteration":604,"passed_time":12.58159168,"remaining_time":8.214427627},
{"learn":[0.1721225941],"iteration":605,"passed_time":12.60160595,"remaining_time":8.193123337},
{"learn":[0.1718729973],"iteration":606,"passed_time":12.62034814,"remaining_time":8.170999701},
{"learn":[0.1716796155],"iteration":607,"passed_time":12.64046426,"remaining_time":8.149773007},
{"learn":[0.1715388876],"iteration":608,"passed_time":12.65929912,"remaining_time":8.127727348},
{"learn":[0.1712603801],"iteration":609,"passed_time":12.67853955,"remaining_time":8.105951517},
{"learn":[0.170994241],"iteration":610,"passed_time":12.69813473,"remaining_time":8.084409834},
{"learn":[0.1707846362],"iteration":611,"passed_time":12.71899548,"remaining_time":8.063676872},
{"learn":[0.1705942673],"iteration":612,"passed_time":12.73854248,"remaining_time":8.042114095},
{"learn":[0.1703012534],"iteration":613,"passed_time":12.75758828,"remaining_time":8.020242797},
{"learn":[0.170172071],"iteration":614,"passed_time":12.7768079,"remaining_time":7.998489495},
{"learn":[0.1699706052],"iteration":615,"passed_time":12.79722714,"remaining_time":7.977492243},
{"learn":[0.169612045],"iteration":616,"passed_time":12.81741163,"remaining_time":7.956351144},
{"learn":[0.169220932],"iteration":617,"passed_time":12.8380753,"remaining_time":7.935509328},
{"learn":[0.1689730586],"iteration":618,"passed_time":12.85773609,"remaining_time":7.914050806},
{"learn":[0.1687163756],"iteration":619,"passed_time":12.87909336,"remaining_time":7.893637864},
{"learn":[0.1685371778],"iteration":620,"passed_time":12.89962932,"remaining_time":7.872720632},
{"learn":[0.1681906267],"iteration":621,"passed_time":12.92084412,"remaining_time":7.852217165},
{"learn":[0.1679842134],"iteration":622,"passed_time":12.94037964,"remaining_time":7.830695223},
{"learn":[0.1677962046],"iteration":623,"passed_time":12.9597687,"remaining_time":7.809091396},
{"learn":[0.1673679621],"iteration":624,"passed_time":12.98056371,"remaining_time":7.788338228},
{"learn":[0.16714245],"iteration":625,"passed_time":13.00063329,"remaining_time":7.767151516},
{"learn":[0.1670745234],"iteration":626,"passed_time":13.0202079,"remaining_time":7.74567392},
{"learn":[0.1668382633],"iteration":627,"passed_time":13.04046216,"remaining_time":7.724604972},
{"learn":[0.1665768067],"iteration":628,"passed_time":13.05891199,"remaining_time":7.702474324},
{"learn":[0.1662587285],"iteration":629,"passed_time":13.07888389,"remaining_time":7.68124927},
{"learn":[0.1660250535],"iteration":630,"passed_time":13.09915131,"remaining_time":7.660201006},
{"learn":[0.1657574885],"iteration":631,"passed_time":13.11994069,"remaining_time":7.639459136},
{"learn":[0.1655504191],"iteration":632,"passed_time":13.13987516,"remaining_time":7.618221459},
{"learn":[0.1651288337],"iteration":633,"passed_time":13.15882919,"remaining_time":7.596421895},
{"learn":[0.1649208401],"iteration":634,"passed_time":13.17896753,"remaining_time":7.575312044},
{"learn":[0.1647275593],"iteration":635,"passed_time":13.19913593,"remaining_time":7.554222451},
{"learn":[0.1645263177],"iteration":636,"passed_time":13.21891736,"remaining_time":7.532915232},
{"learn":[0.1642501269],"iteration":637,"passed_time":13.23842182,"remaining_time":7.511455639},
{"learn":[0.1640182529],"iteration":638,"passed_time":13.25854703,"remaining_time":7.490352862},
{"learn":[0.1635594177],"iteration":639,"passed_time":13.27859711,"remaining_time":7.469210873},
{"learn":[0.1633463842],"iteration":640,"passed_time":13.29898864,"remaining_time":7.448263527},
{"learn":[0.1631022739],"iteration":641,"passed_time":13.31956996,"remaining_time":7.427423749},
{"learn":[0.1629564705],"iteration":642,"passed_time":13.33872334,"remaining_time":7.405791964},
{"learn":[0.1628768135],"iteration":643,"passed_time":13.35794664,"remaining_time":7.384206528},
{"learn":[0.1627612951],"iteration":644,"passed_time":13.37984156,"remaining_time":7.364098845},
{"learn":[0.1625714423],"iteration":645,"passed_time":13.40073046,"remaining_time":7.343434337},
{"learn":[0.1622483161],"iteration":646,"passed_time":13.42429594,"remaining_time":7.324229472},
{"learn":[0.1618495431],"iteration":647,"passed_time":13.44687027,"remaining_time":7.304472742},
{"learn":[0.161685689],"iteration":648,"passed_time":13.46838165,"remaining_time":7.284132448},
{"learn":[0.1612799349],"iteration":649,"passed_time":13.48997778,"remaining_time":7.26383419},
{"learn":[0.1610771296],"iteration":650,"passed_time":13.51213555,"remaining_time":7.243833037},
{"learn":[0.1607747613],"iteration":651,"passed_time":13.53370159,"remaining_time":7.22350944},
{"learn":[0.1602837555],"iteration":652,"passed_time":13.55473029,"remaining_time":7.202896493},
{"learn":[0.1601144774],"iteration":653,"passed_time":13.5776638,"remaining_time":7.183290022},
{"learn":[0.1597815769],"iteration":654,"passed_time":13.59925971,"remaining_time":7.162968856},
{"learn":[0.1595749543],"iteration":655,"passed_time":13.62011942,"remaining_time":7.142257745},
{"learn":[0.1594038396],"iteration":656,"passed_time":13.64098578,"remaining_time":7.121549651},
{"learn":[0.1591020757],"iteration":657,"passed_time":13.66278236,"remaining_time":7.101324572},
{"learn":[0.1588540235],"iteration":658,"passed_time":13.68396993,"remaining_time":7.080779585},
{"learn":[0.1586855795],"iteration":659,"passed_time":13.70356719,"remaining_time":7.059413403},
{"learn":[0.1585101723],"iteration":660,"passed_time":13.72433493,"remaining_time":7.038652863},
{"learn":[0.1583169558],"iteration":661,"passed_time":13.74555688,"remaining_time":7.018124207},
{"learn":[0.1581752693],"iteration":662,"passed_time":13.76624042,"remaining_time":6.997319791},
{"learn":[0.1580561535],"iteration":663,"passed_time":13.7865741,"remaining_time":6.9763387},
{"learn":[0.1578936592],"iteration":664,"passed_time":13.80778727,"remaining_time":6.955802611},
{"learn":[0.1577711363],"iteration":665,"passed_time":13.82787683,"remaining_time":6.934700992},
{"learn":[0.1575935198],"iteration":666,"passed_time":13.847869,"remaining_time":6.913553788},
{"learn":[0.1572823736],"iteration":667,"passed_time":13.8684534,"remaining_time":6.892704385},
{"learn":[0.1570829602],"iteration":668,"passed_time":13.88841872,"remaining_time":6.871549471},
{"learn":[0.1567801032],"iteration":669,"passed_time":13.9093211,"remaining_time":6.850859648},
{"learn":[0.1563446259],"iteration":670,"passed_time":13.93024253,"remaining_time":6.83017853},
{"learn":[0.1561938505],"iteration":671,"passed_time":13.95175531,"remaining_time":6.809785331},
{"learn":[0.1559771229],"iteration":672,"passed_time":13.9729331,"remaining_time":6.789226037},
{"learn":[0.1556313362],"iteration":673,"passed_time":13.99437261,"remaining_time":6.7687915},
{"learn":[0.1554145517],"iteration":674,"passed_time":14.01417133,"remaining_time":6.747563976},
{"learn":[0.1551523336],"iteration":675,"passed_time":14.03343473,"remaining_time":6.726084101},
{"learn":[0.1549068324],"iteration":676,"passed_time":14.05398867,"remaining_time":6.7052265},
{"learn":[0.1547887239],"iteration":677,"passed_time":14.07343529,"remaining_time":6.683843899},
{"learn":[0.1543312925],"iteration":678,"passed_time":14.09491078,"remaining_time":6.663426158},
{"learn":[0.1542269473],"iteration":679,"passed_time":14.12020911,"remaining_time":6.644804285},
{"learn":[0.1541032912],"iteration":680,"passed_time":14.14513384,"remaining_time":6.625987807},
{"learn":[0.1538760991],"iteration":681,"passed_time":14.17587054,"remaining_time":6.609863389},
{"learn":[0.1535880615],"iteration":682,"passed_time":14.20065168,"remaining_time":6.59093204},
{"learn":[0.1534800852],"iteration":683,"passed_time":14.22635779,"remaining_time":6.572410907},
{"learn":[0.1531386983],"iteration":684,"passed_time":14.2487917,"remaining_time":6.552364064},
{"learn":[0.152981984],"iteration":685,"passed_time":14.26922919,"remaining_time":6.531396452},
{"learn":[0.1528355798],"iteration":686,"passed_time":14.28983859,"remaining_time":6.510508703},
{"learn":[0.1525532581],"iteration":687,"passed_time":14.31076697,"remaining_time":6.489766418},
{"learn":[0.1523784207],"iteration":688,"passed_time":14.33577545,"remaining_time":6.470865262},
{"learn":[0.152037191],"iteration":689,"passed_time":14.36032669,"remaining_time":6.451740978},
{"learn":[0.1518267872],"iteration":690,"passed_time":14.39091959,"remaining_time":6.435302681},
{"learn":[0.1516531857],"iteration":691,"passed_time":14.41676754,"remaining_time":6.416711566},
{"learn":[0.1514870898],"iteration":692,"passed_time":14.44241473,"remaining_time":6.398010567},
{"learn":[0.1512179666],"iteration":693,"passed_time":14.4657126,"remaining_time":6.378253683},
{"learn":[0.1510759385],"iteration":694,"passed_time":14.48781842,"remaining_time":6.357963478},
{"learn":[0.1508762936],"iteration":695,"passed_time":14.51001587,"remaining_time":6.337708082},
{"learn":[0.1506302099],"iteration":696,"passed_time":14.5324281,"remaining_time":6.317540481},
{"learn":[0.1504201711],"iteration":697,"passed_time":14.55665877,"remaining_time":6.29815322},
{"learn":[0.150188346],"iteration":698,"passed_time":14.5783186,"remaining_time":6.277645064},
{"learn":[0.1500611487],"iteration":699,"passed_time":14.60160754,"remaining_time":6.257831801},
{"learn":[0.1497255603],"iteration":700,"passed_time":14.62493528,"remaining_time":6.238025177},
{"learn":[0.1495893796],"iteration":701,"passed_time":14.64790188,"remaining_time":6.218055216},
{"learn":[0.1494697177],"iteration":702,"passed_time":14.66980935,"remaining_time":6.197629268},
{"learn":[0.1493563012],"iteration":703,"passed_time":14.69103219,"remaining_time":6.176911262},
{"learn":[0.1491259283],"iteration":704,"passed_time":14.71353124,"remaining_time":6.156725839},
{"learn":[0.1489373975],"iteration":705,"passed_time":14.73512126,"remaining_time":6.136155312},
{"learn":[0.1487893405],"iteration":706,"passed_time":14.7565795,"remaining_time":6.115527289},
{"learn":[0.1486128688],"iteration":707,"passed_time":14.77746268,"remaining_time":6.094659748},
{"learn":[0.1484441613],"iteration":708,"passed_time":14.79792876,"remaining_time":6.073620971},
{"learn":[0.1482397332],"iteration":709,"passed_time":14.81939888,"remaining_time":6.052993907},
{"learn":[0.1480459739],"iteration":710,"passed_time":14.83963907,"remaining_time":6.031864543},
{"learn":[0.1478103774],"iteration":711,"passed_time":14.86121428,"remaining_time":6.011277686},
{"learn":[0.1476156682],"iteration":712,"passed_time":14.88259398,"remaining_time":5.99060936},
{"learn":[0.147393806],"iteration":713,"passed_time":14.90454954,"remaining_time":5.970169705},
{"learn":[0.1472832421],"iteration":714,"passed_time":14.92866013,"remaining_time":5.950584805},
{"learn":[0.1470531335],"iteration":715,"passed_time":14.95648431,"remaining_time":5.932460256},
{"learn":[0.1468421645],"iteration":716,"passed_time":14.98325004,"remaining_time":5.91389088},
{"learn":[0.1466662965],"iteration":717,"passed_time":15.01352943,"remaining_time":5.896678691},
{"learn":[0.1461986588],"iteration":718,"passed_time":15.04463496,"remaining_time":5.879753024},
{"learn":[0.1460311379],"iteration":719,"passed_time":15.0725781,"remaining_time":5.86155815},
{"learn":[0.1458347985],"iteration":720,"passed_time":15.0989648,"remaining_time":5.84273395},
{"learn":[0.1457442015],"iteration":721,"passed_time":15.12733499,"remaining_time":5.824652531},
{"learn":[0.1455502628],"iteration":722,"passed_time":15.15768489,"remaining_time":5.807301127},
{"learn":[0.1454226645],"iteration":723,"passed_time":15.1863408,"remaining_time":5.78926804},
{"learn":[0.1452765895],"iteration":724,"passed_time":15.21254424,"remaining_time":5.7702754},
{"learn":[0.1450604434],"iteration":725,"passed_time":15.24148706,"remaining_time":5.75229677},
{"learn":[0.1448487991],"iteration":726,"passed_time":15.26885946,"remaining_time":5.733698255},
{"learn":[0.1447323025],"iteration":727,"passed_time":15.29512998,"remaining_time":5.714663949},
{"learn":[0.1446135396],"iteration":728,"passed_time":15.32032301,"remaining_time":5.69520924},
{"learn":[0.1444116292],"iteration":729,"passed_time":15.34644318,"remaining_time":5.676081724},
{"learn":[0.1440905209],"iteration":730,"passed_time":15.37460006,"remaining_time":5.657684562},
{"learn":[0.1439861476],"iteration":731,"passed_time":15.40371984,"remaining_time":5.639613276},
{"learn":[0.1438125946],"iteration":732,"passed_time":15.42670761,"remaining_time":5.619278217},
{"learn":[0.1435666417],"iteration":733,"passed_time":15.4545042,"remaining_time":5.600678633},
{"learn":[0.143469201],"iteration":734,"passed_time":15.4798013,"remaining_time":5.581152848},
{"learn":[0.1433600983],"iteration":735,"passed_time":15.50619359,"remaining_time":5.562004224},
{"learn":[0.1431008429],"iteration":736,"passed_time":15.53372945,"remaining_time":5.543244022},
{"learn":[0.1427230104],"iteration":737,"passed_time":15.55825619,"remaining_time":5.523391764},
{"learn":[0.1425502403],"iteration":738,"passed_time":15.58498823,"remaining_time":5.50430572},
{"learn":[0.1422162303],"iteration":739,"passed_time":15.61083021,"remaining_time":5.484886291},
{"learn":[0.142047008],"iteration":740,"passed_time":15.66698888,"remaining_time":5.476046045},
{"learn":[0.1419732473],"iteration":741,"passed_time":15.7063742,"remaining_time":5.461246015},
{"learn":[0.1417107156],"iteration":742,"passed_time":15.73889134,"remaining_time":5.444004138},
{"learn":[0.1414716052],"iteration":743,"passed_time":15.76449454,"remaining_time":5.424342208},
{"learn":[0.1413331624],"iteration":744,"passed_time":15.78989797,"remaining_time":5.404595948},
{"learn":[0.1412241554],"iteration":745,"passed_time":15.81561879,"remaining_time":5.38494259},
{"learn":[0.1411226422],"iteration":746,"passed_time":15.83842909,"remaining_time":5.364287229},
{"learn":[0.1409544244],"iteration":747,"passed_time":15.86125356,"remaining_time":5.343630878},
{"learn":[0.1408787775],"iteration":748,"passed_time":15.88541918,"remaining_time":5.323418177},
{"learn":[0.1406539906],"iteration":749,"passed_time":15.90861859,"remaining_time":5.302872864},
{"learn":[0.1404843174],"iteration":750,"passed_time":15.93305548,"remaining_time":5.282730779},
{"learn":[0.1403772159],"iteration":751,"passed_time":15.95649428,"remaining_time":5.262248115},
{"learn":[0.1401134374],"iteration":752,"passed_time":15.98294646,"remaining_time":5.242746049},
{"learn":[0.1399216949],"iteration":753,"passed_time":16.00764141,"remaining_time":5.222652238},
{"learn":[0.1397975716],"iteration":754,"passed_time":16.03265984,"remaining_time":5.202651207},
{"learn":[0.139693919],"iteration":755,"passed_time":16.05603867,"remaining_time":5.182107719},
{"learn":[0.1396175543],"iteration":756,"passed_time":16.07806637,"remaining_time":5.161123022},
{"learn":[0.1392871978],"iteration":757,"passed_time":16.09962936,"remaining_time":5.13998721},
{"learn":[0.1390903404],"iteration":758,"passed_time":16.12138382,"remaining_time":5.118911069},
{"learn":[0.1388330859],"iteration":759,"passed_time":16.14361925,"remaining_time":5.097985027},
{"learn":[0.1385395124],"iteration":760,"passed_time":16.1657166,"remaining_time":5.077012179},
{"learn":[0.1382730523],"iteration":761,"passed_time":16.18691498,"remaining_time":5.055755596},
{"learn":[0.1381263153],"iteration":762,"passed_time":16.21554149,"remaining_time":5.036806466},
{"learn":[0.1379460035],"iteration":763,"passed_time":16.24660975,"remaining_time":5.018586259},
{"learn":[0.1377275482],"iteration":764,"passed_time":16.27364778,"remaining_time":4.999094416},
{"learn":[0.1375449255],"iteration":765,"passed_time":16.30035332,"remaining_time":4.979481301},
{"learn":[0.1373677793],"iteration":766,"passed_time":16.32562822,"remaining_time":4.959415092},
{"learn":[0.137163299],"iteration":767,"passed_time":16.34774507,"remaining_time":4.938381323},
{"learn":[0.1370134813],"iteration":768,"passed_time":16.36989831,"remaining_time":4.917355669},
{"learn":[0.1368296403],"iteration":769,"passed_time":16.39292394,"remaining_time":4.89658767},
{"learn":[0.1366484042],"iteration":770,"passed_time":16.41548557,"remaining_time":4.875676001},
{"learn":[0.1365718383],"iteration":771,"passed_time":16.43736817,"remaining_time":4.854559512},
{"learn":[0.1364237811],"iteration":772,"passed_time":16.45844929,"remaining_time":4.833205678},
{"learn":[0.1361479705],"iteration":773,"passed_time":16.47953264,"remaining_time":4.811853199},
{"learn":[0.1359767126],"iteration":774,"passed_time":16.49993137,"remaining_time":4.790302654},
{"learn":[0.1357369101],"iteration":775,"passed_time":16.52139789,"remaining_time":4.76906331},
{"learn":[0.1356303803],"iteration":776,"passed_time":16.54224342,"remaining_time":4.747645153},
{"learn":[0.1354448847],"iteration":777,"passed_time":16.56214961,"remaining_time":4.72596043},
{"learn":[0.1352030878],"iteration":778,"passed_time":16.58186111,"remaining_time":4.704225039},
{"learn":[0.1350069567],"iteration":779,"passed_time":16.60139717,"remaining_time":4.682445357},
{"learn":[0.1348624863],"iteration":780,"passed_time":16.62062647,"remaining_time":4.660585401},
{"learn":[0.134640431],"iteration":781,"passed_time":16.64077625,"remaining_time":4.638988776},
{"learn":[0.134581273],"iteration":782,"passed_time":16.66072204,"remaining_time":4.617339315},
{"learn":[0.1344777522],"iteration":783,"passed_time":16.68043199,"remaining_time":4.595629223},
{"learn":[0.1343508332],"iteration":784,"passed_time":16.70063047,"remaining_time":4.574058027},
{"learn":[0.1342307353],"iteration":785,"passed_time":16.72041164,"remaining_time":4.552376707},
{"learn":[0.1339600535],"iteration":786,"passed_time":16.74114252,"remaining_time":4.530957251},
{"learn":[0.1338791395],"iteration":787,"passed_time":16.76206081,"remaining_time":4.509589964},
{"learn":[0.1338062745],"iteration":788,"passed_time":16.7844713,"remaining_time":4.488622869},
{"learn":[0.1336911045],"iteration":789,"passed_time":16.80785012,"remaining_time":4.467909526},
{"learn":[0.1335218748],"iteration":790,"passed_time":16.83210221,"remaining_time":4.447420179},
{"learn":[0.1332476119],"iteration":791,"passed_time":16.85775489,"remaining_time":4.427289163},
{"learn":[0.1330473134],"iteration":792,"passed_time":16.87847366,"remaining_time":4.405856302},
{"learn":[0.1327684184],"iteration":793,"passed_time":16.90007507,"remaining_time":4.384654236},
{"learn":[0.1326064682],"iteration":794,"passed_time":16.92411771,"remaining_time":4.364080668},
{"learn":[0.1324400832],"iteration":795,"passed_time":16.94844443,"remaining_time":4.343571185},
{"learn":[0.132312719],"iteration":796,"passed_time":16.97176409,"remaining_time":4.322795621},
{"learn":[0.132161603],"iteration":797,"passed_time":16.99611888,"remaining_time":4.302275707},
{"learn":[0.131937086],"iteration":798,"passed_time":17.01966941,"remaining_time":4.28154387},
{"learn":[0.1318140423],"iteration":799,"passed_time":17.04105288,"remaining_time":4.260263219},
{"learn":[0.131693781],"iteration":800,"passed_time":17.06116393,"remaining_time":4.238666195},
{"learn":[0.1315320408],"iteration":801,"passed_time":17.08176745,"remaining_time":4.217194458},
{"learn":[0.131288463],"iteration":802,"passed_time":17.10285739,"remaining_time":4.195844216},
{"learn":[0.1311938439],"iteration":803,"passed_time":17.12310621,"remaining_time":4.174289574},
{"learn":[0.1310231966],"iteration":804,"passed_time":17.14286908,"remaining_time":4.15262046},
{"learn":[0.1308402436],"iteration":805,"passed_time":17.16449217,"remaining_time":4.131403822},
{"learn":[0.1306574982],"iteration":806,"passed_time":17.18501513,"remaining_time":4.109923073},
{"learn":[0.1306048078],"iteration":807,"passed_time":17.20500983,"remaining_time":4.088319168},
{"learn":[0.1303847117],"iteration":808,"passed_time":17.22745681,"remaining_time":4.067298209},
{"learn":[0.1302033239],"iteration":809,"passed_time":17.25070696,"remaining_time":4.046462127},
{"learn":[0.1301045607],"iteration":810,"passed_time":17.27770538,"remaining_time":4.026493609},
{"learn":[0.1300491276],"iteration":811,"passed_time":17.30404557,"remaining_time":4.006355378},
{"learn":[0.1298290807],"iteration":812,"passed_time":17.3268943,"remaining_time":3.985398813},
{"learn":[0.129692224],"iteration":813,"passed_time":17.35094998,"remaining_time":3.964713387},
{"learn":[0.1295062661],"iteration":814,"passed_time":17.3746614,"remaining_time":3.943941545},
{"learn":[0.1293276719],"iteration":815,"passed_time":17.39922241,"remaining_time":3.923354072},
{"learn":[0.1291809321],"iteration":816,"passed_time":17.42485396,"remaining_time":3.902996663},
{"learn":[0.1289156878],"iteration":817,"passed_time":17.45109912,"remaining_time":3.882762885},
{"learn":[0.128531909],"iteration":818,"passed_time":17.47634621,"remaining_time":3.862293852},
{"learn":[0.1283336147],"iteration":819,"passed_time":17.50248882,"remaining_time":3.842009741},
{"learn":[0.1281486468],"iteration":820,"passed_time":17.52741976,"remaining_time":3.821447183},
{"learn":[0.1280056114],"iteration":821,"passed_time":17.55427159,"remaining_time":3.801289955},
{"learn":[0.12776354],"iteration":822,"passed_time":17.58012922,"remaining_time":3.780902638},
{"learn":[0.1275222313],"iteration":823,"passed_time":17.60702491,"remaining_time":3.760723768},
{"learn":[0.1274309248],"iteration":824,"passed_time":17.63531839,"remaining_time":3.740825113},
{"learn":[0.1272605655],"iteration":825,"passed_time":17.6586444,"remaining_time":3.719859716},
{"learn":[0.1270440822],"iteration":826,"passed_time":17.6830688,"remaining_time":3.699118383},
{"learn":[0.1269374212],"iteration":827,"passed_time":17.70756022,"remaining_time":3.678382075},
{"learn":[0.126746349],"iteration":828,"passed_time":17.73304665,"remaining_time":3.65784195},
{"learn":[0.1266279608],"iteration":829,"passed_time":17.75885095,"remaining_time":3.637355013},
{"learn":[0.1265355356],"iteration":830,"passed_time":17.78720124,"remaining_time":3.617373056},
{"learn":[0.1262108549],"iteration":831,"passed_time":17.81523452,"remaining_time":3.597306971},
{"learn":[0.126061576],"iteration":832,"passed_time":17.84045798,"remaining_time":3.576658443},
{"learn":[0.1259530108],"iteration":833,"passed_time":17.86567692,"remaining_time":3.555998043},
{"learn":[0.1258142657],"iteration":834,"passed_time":17.89058839,"remaining_time":3.535265969},
{"learn":[0.125703907],"iteration":835,"passed_time":17.91822682,"remaining_time":3.51505885},
{"learn":[0.1256151245],"iteration":836,"passed_time":17.94504867,"remaining_time":3.49467495},
{"learn":[0.1255269575],"iteration":837,"passed_time":17.98234974,"remaining_time":3.476301501},
{"learn":[0.1252998145],"iteration":838,"passed_time":18.01273043,"remaining_time":3.456554946},
{"learn":[0.1250835985],"iteration":839,"passed_time":18.04359554,"remaining_time":3.436875342},
{"learn":[0.1249388606],"iteration":840,"passed_time":18.07379919,"remaining_time":3.417044079},
{"learn":[0.1248416962],"iteration":841,"passed_time":18.1039869,"remaining_time":3.39718519},
{"learn":[0.124706537],"iteration":842,"passed_time":18.1334404,"remaining_time":3.377165057},
{"learn":[0.1246357341],"iteration":843,"passed_time":18.15985568,"remaining_time":3.356561003},
{"learn":[0.1245620142],"iteration":844,"passed_time":18.18729442,"remaining_time":3.336130929},
{"learn":[0.1244003702],"iteration":845,"passed_time":18.21774926,"remaining_time":3.316233317},
{"learn":[0.1240869402],"iteration":846,"passed_time":18.24332842,"remaining_time":3.295430044},
{"learn":[0.123975045],"iteration":847,"passed_time":18.26973634,"remaining_time":3.274764061},
{"learn":[0.1237537309],"iteration":848,"passed_time":18.2966274,"remaining_time":3.25417048},
{"learn":[0.1234216444],"iteration":849,"passed_time":18.31911187,"remaining_time":3.232784448},
{"learn":[0.123220346],"iteration":850,"passed_time":18.34376928,"remaining_time":3.21177629},
{"learn":[0.1231623431],"iteration":851,"passed_time":18.36660789,"remaining_time":3.190443624},
{"learn":[0.1230352907],"iteration":852,"passed_time":18.39184298,"remaining_time":3.169520419},
{"learn":[0.1229002448],"iteration":853,"passed_time":18.42385373,"remaining_time":3.149745485},
{"learn":[0.1226659485],"iteration":854,"passed_time":18.45516193,"remaining_time":3.129822783},
{"learn":[0.1225661075],"iteration":855,"passed_time":18.49114054,"remaining_time":3.110659156},
{"learn":[0.1224837609],"iteration":856,"passed_time":18.51932376,"remaining_time":3.090155539},
{"learn":[0.122375703],"iteration":857,"passed_time":18.54380504,"remaining_time":3.069021347},
{"learn":[0.1221467416],"iteration":858,"passed_time":18.56723639,"remaining_time":3.047707021},
{"learn":[0.1219166869],"iteration":859,"passed_time":18.59172997,"remaining_time":3.026560693},
{"learn":[0.1218174186],"iteration":860,"passed_time":18.61564089,"remaining_time":3.005312525},
{"learn":[0.1217315912],"iteration":861,"passed_time":18.63873024,"remaining_time":2.98392665},
{"learn":[0.1216286291],"iteration":862,"passed_time":18.662456,"remaining_time":2.962637859},
{"learn":[0.1214704263],"iteration":863,"passed_time":18.68691238,"remaining_time":2.941458429},
{"learn":[0.1211853373],"iteration":864,"passed_time":18.71120699,"remaining_time":2.920246178},
{"learn":[0.1209712131],"iteration":865,"passed_time":18.73549354,"remaining_time":2.899025559},
{"learn":[0.1208514407],"iteration":866,"passed_time":18.75910684,"remaining_time":2.87769459},
{"learn":[0.1206960455],"iteration":867,"passed_time":18.7820591,"remaining_time":2.856257836},
{"learn":[0.120577368],"iteration":868,"passed_time":18.80459577,"remaining_time":2.834754944},
{"learn":[0.1204151488],"iteration":869,"passed_time":18.82984301,"remaining_time":2.813654703},
{"learn":[0.1203170456],"iteration":870,"passed_time":18.85382781,"remaining_time":2.792357965},
{"learn":[0.1201141805],"iteration":871,"passed_time":18.87819402,"remaining_time":2.771111049},
{"learn":[0.1200148058],"iteration":872,"passed_time":18.90543545,"remaining_time":2.75027526},
{"learn":[0.119834312],"iteration":873,"passed_time":18.93258547,"remaining_time":2.729411635},
{"learn":[0.1196245579],"iteration":874,"passed_time":18.95903717,"remaining_time":2.708433881},
{"learn":[0.1193473435],"iteration":875,"passed_time":18.98504159,"remaining_time":2.687380317},
{"learn":[0.11915572],"iteration":876,"passed_time":19.01078206,"remaining_time":2.666278441},
{"learn":[0.1189333403],"iteration":877,"passed_time":19.03495763,"remaining_time":2.644948554},
{"learn":[0.1185707821],"iteration":878,"passed_time":19.06264799,"remaining_time":2.624096025},
{"learn":[0.1183699699],"iteration":879,"passed_time":19.08915215,"remaining_time":2.603066202},
{"learn":[0.1182156837],"iteration":880,"passed_time":19.11404838,"remaining_time":2.581806762},
{"learn":[0.1180740975],"iteration":881,"passed_time":19.14341876,"remaining_time":2.561137657},
{"learn":[0.117814985],"iteration":882,"passed_time":19.17023638,"remaining_time":2.540110596},
{"learn":[0.1176145124],"iteration":883,"passed_time":19.19556882,"remaining_time":2.518875547},
{"learn":[0.1173854505],"iteration":884,"passed_time":19.2208698,"remaining_time":2.497627149},
{"learn":[0.1172695124],"iteration":885,"passed_time":19.24622994,"remaining_time":2.476377216},
{"learn":[0.1171947869],"iteration":886,"passed_time":19.27162458,"remaining_time":2.45512241},
{"learn":[0.1171494263],"iteration":887,"passed_time":19.29501804,"remaining_time":2.433605879},
{"learn":[0.117051763],"iteration":888,"passed_time":19.31973065,"remaining_time":2.412249834},
{"learn":[0.1168453067],"iteration":889,"passed_time":19.34535732,"remaining_time":2.390999219},
{"learn":[0.1165508572],"iteration":890,"passed_time":19.37099533,"remaining_time":2.36974017},
{"learn":[0.1163741072],"iteration":891,"passed_time":19.39428954,"remaining_time":2.348187523},
{"learn":[0.1161615335],"iteration":892,"passed_time":19.4181151,"remaining_time":2.326694642},
{"learn":[0.1160753409],"iteration":893,"passed_time":19.44360867,"remaining_time":2.305394316},
{"learn":[0.1159511436],"iteration":894,"passed_time":19.46868755,"remaining_time":2.28403597},
{"learn":[0.1156480643],"iteration":895,"passed_time":19.4921551,"remaining_time":2.262482288},
{"learn":[0.1155206337],"iteration":896,"passed_time":19.51608974,"remaining_time":2.240977975},
{"learn":[0.1152900431],"iteration":897,"passed_time":19.54161049,"remaining_time":2.219648407},
{"learn":[0.115073211],"iteration":898,"passed_time":19.56480336,"remaining_time":2.198047986},
{"learn":[0.1149124767],"iteration":899,"passed_time":19.58979901,"remaining_time":2.176644335},
{"learn":[0.1147753765],"iteration":900,"passed_time":19.61368431,"remaining_time":2.155110707},
{"learn":[0.1145757189],"iteration":901,"passed_time":19.63719227,"remaining_time":2.133530868},
{"learn":[0.1144734413],"iteration":902,"passed_time":19.66029719,"remaining_time":2.111903464},
{"learn":[0.1143494253],"iteration":903,"passed_time":19.68426975,"remaining_time":2.090364929},
{"learn":[0.1142394553],"iteration":904,"passed_time":19.70755414,"remaining_time":2.068748777},
{"learn":[0.114125359],"iteration":905,"passed_time":19.73091998,"remaining_time":2.047137393},
{"learn":[0.1140092777],"iteration":906,"passed_time":19.75321357,"remaining_time":2.025412197},
{"learn":[0.1137522701],"iteration":907,"passed_time":19.77541192,"remaining_time":2.003676097},
{"learn":[0.1136140769],"iteration":908,"passed_time":19.79954333,"remaining_time":1.982132501},
{"learn":[0.1134256212],"iteration":909,"passed_time":19.82365622,"remaining_time":1.960581385},
{"learn":[0.113342384],"iteration":910,"passed_time":19.85011488,"remaining_time":1.939253813},
{"learn":[0.113132149],"iteration":911,"passed_time":19.87362654,"remaining_time":1.917630631},
{"learn":[0.1130353976],"iteration":912,"passed_time":19.89712486,"remaining_time":1.89600204},
{"learn":[0.1129318095],"iteration":913,"passed_time":19.92067877,"remaining_time":1.874374589},
{"learn":[0.1127620914],"iteration":914,"passed_time":19.94398921,"remaining_time":1.852720309},
{"learn":[0.1126595206],"iteration":915,"passed_time":19.96804358,"remaining_time":1.831130634},
{"learn":[0.112513733],"iteration":916,"passed_time":19.99090984,"remaining_time":1.809428045},
{"learn":[0.1123399925],"iteration":917,"passed_time":20.01511321,"remaining_time":1.787842357},
{"learn":[0.112201665],"iteration":918,"passed_time":20.03809418,"remaining_time":1.76614323},
{"learn":[0.1121271314],"iteration":919,"passed_time":20.06176859,"remaining_time":1.744501616},
{"learn":[0.1119508399],"iteration":920,"passed_time":20.08400562,"remaining_time":1.722732295},
{"learn":[0.1118835115],"iteration":921,"passed_time":20.1072272,"remaining_time":1.701045251},
{"learn":[0.1116862818],"iteration":922,"passed_time":20.13155679,"remaining_time":1.679447316},
{"learn":[0.1115846924],"iteration":923,"passed_time":20.15479059,"remaining_time":1.657753339},
{"learn":[0.1114318156],"iteration":924,"passed_time":20.17807984,"remaining_time":1.636060528},
{"learn":[0.1113939644],"iteration":925,"passed_time":20.20109829,"remaining_time":1.614342628},
{"learn":[0.1112408276],"iteration":926,"passed_time":20.2251261,"remaining_time":1.592701408},
{"learn":[0.1111542452],"iteration":927,"passed_time":20.24762508,"remaining_time":1.570936429},
{"learn":[0.1110462348],"iteration":928,"passed_time":20.26954675,"remaining_time":1.549125747},
{"learn":[0.1108901492],"iteration":929,"passed_time":20.29238076,"remaining_time":1.527383498},
{"learn":[0.1107770445],"iteration":930,"passed_time":20.31637128,"remaining_time":1.505724617},
{"learn":[0.1106770267],"iteration":931,"passed_time":20.34000835,"remaining_time":1.484034944},
{"learn":[0.110582722],"iteration":932,"passed_time":20.36264761,"remaining_time":1.462269443},
{"learn":[0.1103948957],"iteration":933,"passed_time":20.3858536,"remaining_time":1.440542118},
{"learn":[0.1101778427],"iteration":934,"passed_time":20.410026,"remaining_time":1.418878813},
{"learn":[0.1099858174],"iteration":935,"passed_time":20.43303963,"remaining_time":1.397130915},
{"learn":[0.1098823911],"iteration":936,"passed_time":20.45431849,"remaining_time":1.375263676},
{"learn":[0.1098041569],"iteration":937,"passed_time":20.47838091,"remaining_time":1.353581681},
{"learn":[0.1096476137],"iteration":938,"passed_time":20.50091749,"remaining_time":1.331795492},
{"learn":[0.1094684021],"iteration":939,"passed_time":20.52387394,"remaining_time":1.310034507},
{"learn":[0.1093476089],"iteration":940,"passed_time":20.54603077,"remaining_time":1.288220846},
{"learn":[0.1092050879],"iteration":941,"passed_time":20.56770513,"remaining_time":1.266376749},
{"learn":[0.1090776527],"iteration":942,"passed_time":20.59065836,"remaining_time":1.244610315},
{"learn":[0.108985702],"iteration":943,"passed_time":20.61231567,"remaining_time":1.222764489},
{"learn":[0.1089411251],"iteration":944,"passed_time":20.63347717,"remaining_time":1.200890206},
{"learn":[0.108767626],"iteration":945,"passed_time":20.65633713,"remaining_time":1.179114382},
{"learn":[0.1086677369],"iteration":946,"passed_time":20.67834833,"remaining_time":1.157288766},
{"learn":[0.108384409],"iteration":947,"passed_time":20.70031763,"remaining_time":1.135460461},
{"learn":[0.1083344466],"iteration":948,"passed_time":20.72261519,"remaining_time":1.113649499},
{"learn":[0.1082535177],"iteration":949,"passed_time":20.74435199,"remaining_time":1.091808},
{"learn":[0.108138415],"iteration":950,"passed_time":20.76563064,"remaining_time":1.069943114},
{"learn":[0.1080468796],"iteration":951,"passed_time":20.7873736,"remaining_time":1.04810287},
{"learn":[0.1079808702],"iteration":952,"passed_time":20.80961258,"remaining_time":1.026287294},
{"learn":[0.1079362364],"iteration":953,"passed_time":20.83036354,"remaining_time":1.004399081},
{"learn":[0.1077521934],"iteration":954,"passed_time":20.85181512,"remaining_time":0.9825462622},
{"learn":[0.1076642711],"iteration":955,"passed_time":20.87459689,"remaining_time":0.9607555054},
{"learn":[0.1075876509],"iteration":956,"passed_time":20.89586942,"remaining_time":0.9388948642},
{"learn":[0.1074577917],"iteration":957,"passed_time":20.91612035,"remaining_time":0.9169906626},
{"learn":[0.1073021089],"iteration":958,"passed_time":20.93760916,"remaining_time":0.8951428315},
{"learn":[0.1072295744],"iteration":959,"passed_time":20.95831378,"remaining_time":0.8732630742},
{"learn":[0.1070623762],"iteration":960,"passed_time":20.97905297,"remaining_time":0.8513871654},
{"learn":[0.106980172],"iteration":961,"passed_time":20.99992177,"remaining_time":0.8295187394},
{"learn":[0.1068661158],"iteration":962,"passed_time":21.0216722,"remaining_time":0.8076862631},
{"learn":[0.1067589257],"iteration":963,"passed_time":21.04162889,"remaining_time":0.785786971},
{"learn":[0.1066240784],"iteration":964,"passed_time":21.06142865,"remaining_time":0.7638860132},
{"learn":[0.1064951661],"iteration":965,"passed_time":21.08276344,"remaining_time":0.7420434337},
{"learn":[0.1063458319],"iteration":966,"passed_time":21.10592375,"remaining_time":0.7202642025},
{"learn":[0.1061654359],"iteration":967,"passed_time":21.12595353,"remaining_time":0.698378629},
{"learn":[0.1060256353],"iteration":968,"passed_time":21.14630958,"remaining_time":0.6765073241},
{"learn":[0.1059084805],"iteration":969,"passed_time":21.16662406,"remaining_time":0.6546378575},
{"learn":[0.1058060054],"iteration":970,"passed_time":21.18689651,"remaining_time":0.6327703385},
{"learn":[0.1056256737],"iteration":971,"passed_time":21.20774101,"remaining_time":0.6109225806},
{"learn":[0.1055164988],"iteration":972,"passed_time":21.22712525,"remaining_time":0.5890363635},
{"learn":[0.1053555584],"iteration":973,"passed_time":21.24617348,"remaining_time":0.5671463147},
{"learn":[0.10518277],"iteration":974,"passed_time":21.26696784,"remaining_time":0.5453068676},
{"learn":[0.1050898828],"iteration":975,"passed_time":21.2869013,"remaining_time":0.5234483927},
{"learn":[0.1049436593],"iteration":976,"passed_time":21.30732564,"remaining_time":0.5016054143},
{"learn":[0.1047746078],"iteration":977,"passed_time":21.32591447,"remaining_time":0.4797240474},
{"learn":[0.1047133139],"iteration":978,"passed_time":21.34496049,"remaining_time":0.4578592139},
{"learn":[0.10462743],"iteration":979,"passed_time":21.36491002,"remaining_time":0.4360185718},
{"learn":[0.1045182706],"iteration":980,"passed_time":21.384481,"remaining_time":0.4141744537},
{"learn":[0.1043742421],"iteration":981,"passed_time":21.40418157,"remaining_time":0.3923373404},
{"learn":[0.1042889327],"iteration":982,"passed_time":21.42309198,"remaining_time":0.3704909092},
{"learn":[0.1041862876],"iteration":983,"passed_time":21.44248752,"remaining_time":0.3486583337},
{"learn":[0.103995889],"iteration":984,"passed_time":21.46204316,"remaining_time":0.3268331445},
{"learn":[0.1039033584],"iteration":985,"passed_time":21.48326645,"remaining_time":0.3050362376},
{"learn":[0.1037110757],"iteration":986,"passed_time":21.50339008,"remaining_time":0.2832260092},
{"learn":[0.1036170809],"iteration":987,"passed_time":21.52290181,"remaining_time":0.2614117629},
{"learn":[0.1034110659],"iteration":988,"passed_time":21.54206679,"remaining_time":0.2395983161},
{"learn":[0.1033588131],"iteration":989,"passed_time":21.56139417,"remaining_time":0.2177918603},
{"learn":[0.1032766847],"iteration":990,"passed_time":21.58030487,"remaining_time":0.1959866234},
{"learn":[0.1031624456],"iteration":991,"passed_time":21.5996479,"remaining_time":0.1741907089},
{"learn":[0.1030140027],"iteration":992,"passed_time":21.61975942,"remaining_time":0.152405152},
{"learn":[0.1029207647],"iteration":993,"passed_time":21.63897992,"remaining_time":0.130617585},
{"learn":[0.1028291442],"iteration":994,"passed_time":21.65733827,"remaining_time":0.1088308456},
{"learn":[0.1027515684],"iteration":995,"passed_time":21.67647084,"remaining_time":0.08705409974},
{"learn":[0.102675941],"iteration":996,"passed_time":21.69531065,"remaining_time":0.06528177728},
{"learn":[0.1025940326],"iteration":997,"passed_time":21.71531536,"remaining_time":0.04351766606},
{"learn":[0.1024597759],"iteration":998,"passed_time":21.73510399,"remaining_time":0.02175686085},
{"learn":[0.1023274521],"iteration":999,"passed_time":21.75381593,"remaining_time":0}
]}